{
  "market": "nasdaq",
  "label": "NASDAQ",
  "setup_type": "reversal",
  "currency": "USD",
  "currency_symbol": "$",
  "timezone": "America/New_York",
  "tz_label": "ET",
  "generated_at": "2026-06-19T00:52:57-04:00",
  "scanned": 98,
  "universe_size": 98,
  "score_max": 14,
  "sma_periods": [
    9,
    26,
    43,
    200
  ],
  "pulse": [
    {
      "key": "ASX200",
      "label": "ASX 200",
      "value": 8809.0,
      "decimals": 0,
      "day_pct": -1.75,
      "d5_pct": 2.04,
      "spark": [
        8604.7002,
        8496.5996,
        8621.7002,
        8657.0,
        8692.0,
        8657.7998,
        8717.7002,
        8592.9004,
        8731.7002,
        8729.4004,
        8724.4004,
        8785.7002,
        8686.0996,
        8625.0996,
        8604.2002,
        8653.2998,
        8633.2002,
        8804.0,
        8914.0,
        8917.7002,
        8966.2998,
        8809.0
      ],
      "dir": "down"
    },
    {
      "key": "GOLD",
      "label": "Gold",
      "value": 4154.0,
      "decimals": 0,
      "day_pct": -1.66,
      "d5_pct": -1.44,
      "spark": [
        4531.2998,
        4539.7998,
        4521.0,
        4500.3999,
        4447.5,
        4499.2998,
        4560.5,
        4475.2002,
        4489.1001,
        4436.7002,
        4475.7998,
        4337.1001,
        4335.8999,
        4260.0,
        4108.2002,
        4090.3,
        4215.0,
        4328.0,
        4330.8999,
        4358.8999,
        4224.1001,
        4154.1001
      ],
      "dir": "down"
    },
    {
      "key": "SILVER",
      "label": "Silver",
      "value": 63.85,
      "decimals": 2,
      "day_pct": -3.63,
      "d5_pct": -5.91,
      "spark": [
        75.851,
        76.414,
        75.893,
        76.305,
        74.599,
        75.645,
        75.616,
        75.007,
        75.311,
        73.476,
        73.779,
        68.943,
        68.425,
        65.094,
        64.599,
        63.885,
        67.859,
        70.066,
        69.899,
        70.696,
        66.255,
        63.85
      ],
      "dir": "down"
    },
    {
      "key": "BRENT",
      "label": "Brent",
      "value": 79.57,
      "decimals": 2,
      "day_pct": -0.35,
      "d5_pct": -8.89,
      "spark": [
        105.02,
        102.58,
        103.54,
        99.58,
        94.29,
        93.71,
        92.05,
        94.98,
        96.0,
        97.81,
        95.03,
        93.09,
        94.25,
        91.45,
        93.1,
        90.38,
        87.33,
        83.17,
        78.96,
        79.55,
        79.85,
        79.57
      ],
      "dir": "down"
    },
    {
      "key": "WTI",
      "label": "WTI",
      "value": 75.68,
      "decimals": 2,
      "day_pct": -1.2,
      "d5_pct": -10.84,
      "spark": [
        98.26,
        96.35,
        96.6,
        93.89,
        88.68,
        88.9,
        87.36,
        92.16,
        93.76,
        96.02,
        93.04,
        90.54,
        91.3,
        88.2,
        90.03,
        87.71,
        84.88,
        80.75,
        76.05,
        76.79,
        76.6,
        75.68
      ],
      "dir": "down"
    },
    {
      "key": "NATGAS",
      "label": "Nat Gas",
      "value": 3.2,
      "decimals": 2,
      "day_pct": -1.02,
      "d5_pct": 2.56,
      "spark": [
        3.004,
        3.018,
        2.907,
        2.894,
        3.04,
        3.285,
        3.29,
        3.179,
        3.167,
        3.214,
        3.336,
        3.229,
        3.147,
        3.14,
        3.185,
        3.087,
        3.12,
        3.147,
        3.239,
        3.145,
        3.233,
        3.2
      ],
      "dir": "down"
    },
    {
      "key": "TECH",
      "label": "Tech",
      "value": 26021.66,
      "decimals": 2,
      "day_pct": -1.34,
      "d5_pct": 3.39,
      "spark": [
        26090.7305,
        25870.7109,
        26270.3594,
        26293.0996,
        26343.9707,
        26656.1797,
        26674.7305,
        26917.4707,
        26972.6191,
        27086.8105,
        27093.9004,
        26853.9805,
        26830.9609,
        25709.4297,
        25929.6602,
        25678.8203,
        25169.5,
        25809.6602,
        25888.8398,
        26683.9395,
        26376.3398,
        26021.6602
      ],
      "dir": "down"
    },
    {
      "key": "BIOTECH",
      "label": "Biotech",
      "value": 139.39,
      "decimals": 2,
      "day_pct": 2.99,
      "d5_pct": 8.18,
      "spark": [
        127.67,
        126.79,
        131.71,
        132.78,
        131.66,
        133.35,
        134.45,
        135.99,
        136.69,
        133.62,
        127.76,
        129.83,
        133.42,
        128.67,
        128.43,
        131.38,
        128.85,
        132.74,
        133.79,
        136.4,
        135.34,
        139.39
      ],
      "dir": "up"
    },
    {
      "key": "YIELDS",
      "label": "10Y",
      "value": 4.451,
      "decimals": 3,
      "day_pct": -0.8,
      "d5_pct": -2.22,
      "spark": [
        4.461,
        4.595,
        4.623,
        4.667,
        4.572,
        4.586,
        4.558,
        4.493,
        4.481,
        4.455,
        4.453,
        4.475,
        4.455,
        4.491,
        4.477,
        4.536,
        4.552,
        4.528,
        4.542,
        4.463,
        4.487,
        4.451
      ],
      "dir": "down"
    },
    {
      "key": "AUD",
      "label": "AUD/USD",
      "value": 0.6996,
      "decimals": 4,
      "day_pct": -0.31,
      "d5_pct": -0.73,
      "spark": [
        0.715,
        0.7148,
        0.7157,
        0.717,
        0.7171,
        0.7133,
        0.7164,
        0.718,
        0.7164,
        0.7174,
        0.7134,
        0.7132,
        0.7043,
        0.704,
        0.7023,
        0.6994,
        0.7048,
        0.7075,
        0.7073,
        0.7066,
        0.7018,
        0.6996
      ],
      "dir": "down"
    },
    {
      "key": "VIX",
      "label": "VIX",
      "value": 16.4,
      "decimals": 2,
      "day_pct": -11.06,
      "d5_pct": -15.64,
      "spark": [
        17.44,
        16.76,
        16.7,
        16.59,
        17.01,
        16.29,
        15.74,
        15.32,
        16.05,
        15.77,
        16.06,
        15.4,
        21.51,
        18.92,
        19.87,
        22.22,
        19.44,
        17.68,
        16.2,
        16.41,
        18.44,
        16.4
      ],
      "dir": "down"
    },
    {
      "key": "USD",
      "label": "USD Idx",
      "value": 101.0,
      "decimals": 2,
      "day_pct": 0.91,
      "d5_pct": 1.14,
      "spark": [
        99.3,
        99.11,
        99.19,
        99.32,
        99.17,
        99.21,
        99.02,
        98.91,
        99.2,
        99.22,
        99.53,
        99.41,
        100.07,
        100.05,
        99.91,
        99.95,
        99.86,
        99.75,
        99.63,
        99.54,
        100.09,
        101.0
      ],
      "dir": "up"
    }
  ],
  "sector_counts": {},
  "results": [
    {
      "symbol": "BKNG",
      "name": "Booking Holdings",
      "sector": "",
      "dir": "LONG",
      "setup_type": "reversal",
      "grade": "B",
      "score": 7,
      "score_max": 14,
      "chips": [
        "9 \u203a 26 RECLAIM",
        "BASE -26% OFF HIGH"
      ],
      "weekly": false,
      "low_rr": true,
      "rr_text": "1.4:1",
      "target_2r": false,
      "liquidity": "LIQUID",
      "price": 171.63000488,
      "y_close": 175.72000122,
      "open": 174.77999878,
      "open_pct": -0.53,
      "current_pct": -1.8,
      "day_pct": -2.33,
      "entry": 171.63000488,
      "stop": 156.53879517,
      "target": 193.43371763,
      "rr": 1.44,
      "trail": 157.12115279,
      "stop_pct": 8.8,
      "p2_pct": 12.7,
      "target_basis": "resistance",
      "spark": [
        167.8979187,
        170.85049438,
        165.51390076,
        157.40429688,
        160.15737915,
        154.64123535,
        154.09262085,
        153.74349976,
        154.68115234,
        154.15246582,
        156.556427,
        159.27957153,
        160.65611267,
        162.89050293,
        167.94778442,
        169.39416504,
        167.01014709,
        168.82557678,
        166.79071045,
        164.36679077,
        167.07000732,
        165.83999634,
        162.30000305,
        163.99000549,
        160.63999939,
        163.58999634,
        164.94000244,
        174.63999939,
        175.72000122,
        171.63000488
      ],
      "trend": "blue",
      "turnover": 1236365699,
      "detail": {
        "setup_type": "reversal",
        "sma9": 167.03222317,
        "sma9_pct": -2.7,
        "sma26": 163.29023684,
        "sma26_pct": -4.9,
        "sma43": 167.64666819,
        "sma43_pct": -2.3,
        "sma200": 190.06339951,
        "sma200_pct": 10.7,
        "cross_up": true,
        "rsi": 56.3,
        "rsi_ma": 51.8,
        "rsi_up": false,
        "volume_ratio": 1.0,
        "volume_today": 5895000,
        "volume_avg": 7582000,
        "volume_surge": false,
        "off_high_pct": 25.9,
        "base_high": 193.43371763,
        "base_high_pct": 12.7,
        "broken": false,
        "swing_low": 158.11999512,
        "swing_low_pct": -7.9,
        "trailing_stop": 157.12115279,
        "trailing_label": "SuperTrend 3\u00d7 ATR",
        "trailing_pct": -8.5,
        "structure": {
          "trend": "Mixed / consolidating",
          "swing_highs": [
            175.07986054,
            170.82056144,
            171.91999817
          ],
          "swing_lows": [
            149.76350629,
            162.01271334,
            158.11999512
          ]
        },
        "risk_pct": 8.8
      },
      "analysis": "BKNG has reclaimed its short-term moving averages \u2014 the 9 has crossed up through the 26 and price is back above both. It is coming off a base, 26% below its one-year high, so there is room to run. Trade idea: entry $171.6300, stop $156.5388, target $193.4337 (1.44:1) \u2014 then trail it.",
      "sector_count": 0
    },
    {
      "symbol": "VRTX",
      "name": "Vertex Pharmaceuticals",
      "sector": "",
      "dir": "LONG",
      "setup_type": "reversal",
      "grade": "B",
      "score": 7,
      "score_max": 14,
      "chips": [
        "BASE -10% OFF HIGH",
        "BASE BREAKOUT",
        "RSI TURNING UP"
      ],
      "weekly": false,
      "low_rr": true,
      "rr_text": "1.1:1",
      "target_2r": false,
      "liquidity": "LIQUID",
      "price": 458.98999023,
      "y_close": 453.17001343,
      "open": 449.67001343,
      "open_pct": -0.77,
      "current_pct": 2.07,
      "day_pct": 1.28,
      "entry": 458.98999023,
      "stop": 415.80990967,
      "target": 507.92001343,
      "rr": 1.13,
      "trail": 421.43834484,
      "stop_pct": 9.4,
      "p2_pct": 10.7,
      "target_basis": "resistance",
      "spark": [
        427.6499939,
        425.0,
        429.82000732,
        435.17001343,
        448.29000854,
        453.05999756,
        450.41000366,
        436.95001221,
        436.57998657,
        434.30999756,
        430.44000244,
        433.54000854,
        434.51998901,
        435.92999268,
        437.22000122,
        447.97000122,
        447.54000854,
        438.3999939,
        425.08999634,
        428.33999634,
        441.73999023,
        446.82998657,
        442.95999146,
        445.76998901,
        435.70999146,
        445.04000854,
        444.92999268,
        450.45999146,
        453.17001343,
        458.98999023
      ],
      "trend": "blue",
      "turnover": 589285999,
      "detail": {
        "setup_type": "reversal",
        "sma9": 447.09555054,
        "sma9_pct": -2.6,
        "sma26": 441.69961313,
        "sma26_pct": -3.8,
        "sma43": 437.36651186,
        "sma43_pct": -4.7,
        "sma200": 439.37974915,
        "sma200_pct": -4.3,
        "cross_up": true,
        "rsi": 61.9,
        "rsi_ma": 53.2,
        "rsi_up": true,
        "volume_ratio": 1.0,
        "volume_today": 1524000,
        "volume_avg": 1319870,
        "volume_surge": false,
        "off_high_pct": 9.6,
        "base_high": 456.67999268,
        "base_high_pct": -0.5,
        "broken": true,
        "swing_low": 420.01000977,
        "swing_low_pct": -8.5,
        "trailing_stop": 421.43834484,
        "trailing_label": "SuperTrend 3\u00d7 ATR",
        "trailing_pct": -8.2,
        "structure": {
          "trend": "Mixed / consolidating",
          "swing_highs": [
            456.67999268,
            450.0,
            453.16000366
          ],
          "swing_lows": [
            426.01000977,
            420.01000977,
            433.79998779
          ]
        },
        "risk_pct": 9.4
      },
      "analysis": "VRTX's 9-SMA is above the 26 and price has reclaimed them. It is coming off a base, 10% below its one-year high, so there is room to run. Price has broken above the base high at $456.6800. RSI has turned up through its signal line. Trade idea: entry $458.9900, stop $415.8099, target $507.9200 (1.13:1) \u2014 then trail it.",
      "sector_count": 0
    },
    {
      "symbol": "DASH",
      "name": "DoorDash",
      "sector": "",
      "dir": "LONG",
      "setup_type": "reversal",
      "grade": "B",
      "score": 7,
      "score_max": 14,
      "chips": [
        "9 \u203a 26 RECLAIM",
        "BASE -42% OFF HIGH"
      ],
      "weekly": false,
      "low_rr": true,
      "rr_text": "0.8:1",
      "target_2r": false,
      "liquidity": "LIQUID",
      "price": 165.66000366,
      "y_close": 170.02999878,
      "open": 169.66999817,
      "open_pct": -0.21,
      "current_pct": -2.36,
      "day_pct": -2.57,
      "entry": 165.66000366,
      "stop": 144.6489006,
      "target": 183.25,
      "rr": 0.84,
      "trail": 173.68636313,
      "stop_pct": 12.7,
      "p2_pct": 10.6,
      "target_basis": "resistance",
      "spark": [
        167.97000122,
        171.3500061,
        163.92999268,
        157.33000183,
        155.19000244,
        149.07000732,
        153.69999695,
        159.19999695,
        162.66999817,
        154.6499939,
        160.72999573,
        159.27000427,
        160.25,
        154.0,
        157.58000183,
        156.69999695,
        159.28999329,
        164.77999878,
        156.94999695,
        154.58000183,
        160.07000732,
        156.80000305,
        152.49000549,
        155.66999817,
        151.0,
        154.58999634,
        150.58000183,
        168.08999634,
        170.02999878,
        165.66000366
      ],
      "trend": "blue",
      "turnover": 763612507,
      "detail": {
        "setup_type": "reversal",
        "sma9": 158.32333374,
        "sma9_pct": -4.4,
        "sma26": 157.83038447,
        "sma26_pct": -4.7,
        "sma43": 164.06790693,
        "sma43_pct": -1.0,
        "sma200": 202.75124985,
        "sma200_pct": 22.4,
        "cross_up": true,
        "rsi": 54.4,
        "rsi_ma": 48.2,
        "rsi_up": false,
        "volume_ratio": 1.1,
        "volume_today": 5354900,
        "volume_avg": 4836720,
        "volume_surge": false,
        "off_high_pct": 42.0,
        "base_high": 191.16999817,
        "base_high_pct": 15.4,
        "broken": false,
        "swing_low": 146.11000061,
        "swing_low_pct": -11.8,
        "trailing_stop": 173.68636313,
        "trailing_label": "SuperTrend 3\u00d7 ATR",
        "trailing_pct": 4.8,
        "structure": {
          "trend": "Mixed / consolidating",
          "swing_highs": [
            163.97000122,
            165.24000549,
            166.52000427
          ],
          "swing_lows": [
            146.80999756,
            151.66000366,
            146.11000061
          ]
        },
        "risk_pct": 12.7
      },
      "analysis": "DASH has reclaimed its short-term moving averages \u2014 the 9 has crossed up through the 26 and price is back above both. It is coming off a base, 42% below its one-year high, so there is room to run. Trade idea: entry $165.6600, stop $144.6489, target $183.2500 (0.84:1) \u2014 then trail it.",
      "sector_count": 0
    },
    {
      "symbol": "ABNB",
      "name": "Airbnb",
      "sector": "",
      "dir": "LONG",
      "setup_type": "reversal",
      "grade": "B",
      "score": 6,
      "score_max": 14,
      "chips": [
        "9 \u203a 26 RECLAIM",
        "RSI TURNING UP"
      ],
      "weekly": false,
      "low_rr": false,
      "rr_text": "3.0:1",
      "target_2r": true,
      "liquidity": "LIQUID",
      "price": 140.53999329,
      "y_close": 141.19999695,
      "open": 140.69000244,
      "open_pct": -0.36,
      "current_pct": -0.11,
      "day_pct": -0.47,
      "entry": 140.53999329,
      "stop": 125.95770332,
      "target": 184.28686317,
      "rr": 3.0,
      "trail": 142.2173079,
      "stop_pct": 10.4,
      "p2_pct": 31.1,
      "target_basis": "measured",
      "spark": [
        139.88000488,
        140.46000671,
        141.49000549,
        137.05000305,
        135.47999573,
        132.97000122,
        133.66999817,
        132.8500061,
        134.30000305,
        131.16000366,
        135.55000305,
        134.25,
        132.3500061,
        132.67999268,
        132.1000061,
        134.5,
        133.30999756,
        137.86999512,
        134.3500061,
        133.58999634,
        133.72000122,
        133.53999329,
        134.42999268,
        131.3500061,
        129.1000061,
        130.86999512,
        132.27999878,
        138.96000671,
        141.19999695,
        140.53999329
      ],
      "trend": "blue",
      "turnover": 514059571,
      "detail": {
        "setup_type": "reversal",
        "sma9": 134.69666545,
        "sma9_pct": -4.2,
        "sma26": 134.11423082,
        "sma26_pct": -4.6,
        "sma43": 136.8255814,
        "sma43_pct": -2.6,
        "sma200": 129.08187492,
        "sma200_pct": -8.2,
        "cross_up": true,
        "rsi": 60.4,
        "rsi_ma": 49.5,
        "rsi_up": true,
        "volume_ratio": 1.0,
        "volume_today": 3438000,
        "volume_avg": 3839970,
        "volume_surge": false,
        "off_high_pct": 4.6,
        "base_high": 147.25,
        "base_high_pct": 4.8,
        "broken": false,
        "swing_low": 127.23000336,
        "swing_low_pct": -9.5,
        "trailing_stop": 142.2173079,
        "trailing_label": "SuperTrend 3\u00d7 ATR",
        "trailing_pct": 1.2,
        "structure": {
          "trend": "LH/LL \u2014 Downtrend",
          "swing_highs": [
            146.97000122,
            137.25999451,
            138.03999329
          ],
          "swing_lows": [
            128.19999695,
            129.69599915,
            127.23000336
          ]
        },
        "risk_pct": 10.4
      },
      "analysis": "ABNB has reclaimed its short-term moving averages \u2014 the 9 has crossed up through the 26 and price is back above both. RSI has turned up through its signal line. Trade idea: entry $140.5400, stop $125.9577, target $184.2869 (3.00:1) \u2014 then trail it.",
      "sector_count": 0
    },
    {
      "symbol": "KDP",
      "name": "Keurig Dr Pepper",
      "sector": "",
      "dir": "LONG",
      "setup_type": "reversal",
      "grade": "B",
      "score": 6,
      "score_max": 14,
      "chips": [
        "BASE -12% OFF HIGH",
        "VOLUME 1.4\u00d7 SURGE"
      ],
      "weekly": false,
      "low_rr": false,
      "rr_text": "3.0:1",
      "target_2r": true,
      "liquidity": "LIQUID",
      "price": 30.88999939,
      "y_close": 32.0,
      "open": 31.86000061,
      "open_pct": -0.44,
      "current_pct": -3.04,
      "day_pct": -3.47,
      "entry": 30.88999939,
      "stop": 29.62080008,
      "target": 34.69759733,
      "rr": 3.0,
      "trail": 29.93039942,
      "stop_pct": 4.1,
      "p2_pct": 12.3,
      "target_basis": "measured",
      "spark": [
        28.55999947,
        28.52000046,
        28.82999992,
        28.70999908,
        29.17000008,
        29.30999947,
        29.10000038,
        28.93000031,
        29.43000031,
        28.85000038,
        28.69000053,
        28.78000069,
        29.12000084,
        29.54999924,
        30.10000038,
        30.04000092,
        30.03000069,
        30.20000076,
        30.36000061,
        30.54999924,
        30.05999947,
        30.53000069,
        30.75,
        31.47999954,
        31.70000076,
        31.22999954,
        31.70999908,
        31.77000046,
        32.0,
        30.88999939
      ],
      "trend": "blue",
      "turnover": 392915697,
      "detail": {
        "setup_type": "reversal",
        "sma9": 31.33999994,
        "sma9_pct": 1.5,
        "sma26": 30.16653861,
        "sma26_pct": -2.3,
        "sma43": 29.41534898,
        "sma43_pct": -4.8,
        "sma200": 27.64635522,
        "sma200_pct": -10.5,
        "cross_up": true,
        "rsi": 56.4,
        "rsi_ma": 67.6,
        "rsi_up": false,
        "volume_ratio": 1.4,
        "volume_today": 17007100,
        "volume_avg": 12611220,
        "volume_surge": true,
        "off_high_pct": 11.8,
        "base_high": 32.27999878,
        "base_high_pct": 4.5,
        "broken": false,
        "swing_low": 29.92000008,
        "swing_low_pct": -3.1,
        "trailing_stop": 29.93039942,
        "trailing_label": "SuperTrend 3\u00d7 ATR",
        "trailing_pct": -3.1,
        "structure": {
          "trend": "HH/HL \u2014 Uptrend",
          "swing_highs": [
            30.54000092,
            31.04000092,
            32.27999878
          ],
          "swing_lows": [
            25.55999947,
            27.84000015,
            28.28000069
          ]
        },
        "risk_pct": 4.1
      },
      "analysis": "KDP's 9-SMA is above the 26 and price has reclaimed them. It is coming off a base, 12% below its one-year high, so there is room to run. Volume is expanding (1.4\u00d7 the 20-day average) \u2014 real participation. Trade idea: entry $30.8900, stop $29.6208, target $34.6976 (3.00:1) \u2014 then trail it.",
      "sector_count": 0
    },
    {
      "symbol": "HON",
      "name": "Honeywell International",
      "sector": "",
      "dir": "LONG",
      "setup_type": "reversal",
      "grade": "C",
      "score": 5,
      "score_max": 14,
      "chips": [
        "BASE -7% OFF HIGH",
        "RSI TURNING UP"
      ],
      "weekly": false,
      "low_rr": false,
      "rr_text": "3.0:1",
      "target_2r": true,
      "liquidity": "LIQUID",
      "price": 228.61000061,
      "y_close": 229.49000549,
      "open": 230.44000244,
      "open_pct": 0.41,
      "current_pct": -0.79,
      "day_pct": -0.38,
      "entry": 228.61000061,
      "stop": 203.46480423,
      "target": 304.04558975,
      "rr": 3.0,
      "trail": 229.63228544,
      "stop_pct": 11.0,
      "p2_pct": 33.0,
      "target_basis": "measured",
      "spark": [
        215.67469788,
        214.88902283,
        211.95513916,
        217.91239929,
        217.34550476,
        216.76869202,
        216.52999878,
        213.24000549,
        217.22999573,
        217.1499939,
        217.38999939,
        223.80000305,
        227.91999817,
        231.72000122,
        231.55000305,
        233.0,
        237.86000061,
        236.53999329,
        235.22999573,
        223.25999451,
        217.63999939,
        213.97000122,
        211.80000305,
        215.69999695,
        205.88000488,
        219.11999512,
        220.30999756,
        227.41000366,
        229.49000549,
        228.61000061
      ],
      "trend": "blue",
      "turnover": 1181051979,
      "detail": {
        "setup_type": "reversal",
        "sma9": 219.14333428,
        "sma9_pct": -4.1,
        "sma26": 222.55631491,
        "sma26_pct": -2.6,
        "sma43": 219.6573536,
        "sma43_pct": -3.9,
        "sma200": 211.33380524,
        "sma200_pct": -7.6,
        "cross_up": false,
        "rsi": 56.1,
        "rsi_ma": 51.5,
        "rsi_up": true,
        "volume_ratio": 1.1,
        "volume_today": 5988800,
        "volume_avg": 5212040,
        "volume_surge": false,
        "off_high_pct": 7.4,
        "base_high": 239.94000244,
        "base_high_pct": 5.0,
        "broken": false,
        "swing_low": 205.52000427,
        "swing_low_pct": -10.1,
        "trailing_stop": 229.63228544,
        "trailing_label": "SuperTrend 3\u00d7 ATR",
        "trailing_pct": 0.4,
        "structure": {
          "trend": "Mixed / consolidating",
          "swing_highs": [
            235.15762661,
            219.8318431,
            239.94000244
          ],
          "swing_lows": [
            207.40016582,
            211.5,
            205.52000427
          ]
        },
        "risk_pct": 11.0
      },
      "analysis": "It is coming off a base, 7% below its one-year high, so there is room to run. RSI has turned up through its signal line. Trade idea: entry $228.6100, stop $203.4648, target $304.0456 (3.00:1) \u2014 then trail it.",
      "sector_count": 0
    },
    {
      "symbol": "TTWO",
      "name": "Take-Two Interactive",
      "sector": "",
      "dir": "LONG",
      "setup_type": "reversal",
      "grade": "C",
      "score": 5,
      "score_max": 14,
      "chips": [
        "BASE -14% OFF HIGH",
        "RSI TURNING UP"
      ],
      "weekly": false,
      "low_rr": true,
      "rr_text": "1.3:1",
      "target_2r": false,
      "liquidity": "LIQUID",
      "price": 228.02999878,
      "y_close": 229.97000122,
      "open": 227.83000183,
      "open_pct": -0.93,
      "current_pct": 0.09,
      "day_pct": -0.84,
      "entry": 228.02999878,
      "stop": 203.94,
      "target": 260.04000854,
      "rr": 1.33,
      "trail": 232.64632242,
      "stop_pct": 10.6,
      "p2_pct": 14.0,
      "target_basis": "resistance",
      "spark": [
        222.0,
        223.5,
        220.44999695,
        221.47000122,
        225.99000549,
        226.99000549,
        242.41000366,
        242.44000244,
        242.16000366,
        238.13999939,
        236.61999512,
        238.08000183,
        227.55000305,
        220.66999817,
        218.46000671,
        217.86999512,
        224.16000366,
        226.97999573,
        222.38000488,
        215.80000305,
        216.6499939,
        214.38999939,
        212.55000305,
        212.05000305,
        210.46000671,
        212.08000183,
        211.75,
        216.22999573,
        229.97000122,
        228.02999878
      ],
      "trend": "blue",
      "turnover": 638568539,
      "detail": {
        "setup_type": "reversal",
        "sma9": 216.39000109,
        "sma9_pct": -5.1,
        "sma26": 224.26384735,
        "sma26_pct": -1.7,
        "sma43": 221.48511629,
        "sma43_pct": -2.9,
        "sma200": 230.88859993,
        "sma200_pct": 1.3,
        "cross_up": false,
        "rsi": 58.5,
        "rsi_ma": 46.1,
        "rsi_up": true,
        "volume_ratio": 0.8,
        "volume_today": 2674900,
        "volume_avg": 2824430,
        "volume_surge": false,
        "off_high_pct": 13.9,
        "base_high": 247.0,
        "base_high_pct": 8.3,
        "broken": false,
        "swing_low": 206.0,
        "swing_low_pct": -9.7,
        "trailing_stop": 232.64632242,
        "trailing_label": "SuperTrend 3\u00d7 ATR",
        "trailing_pct": 2.0,
        "structure": {
          "trend": "LH/LL \u2014 Downtrend",
          "swing_highs": [
            246.25,
            247.0,
            231.02000427
          ],
          "swing_lows": [
            206.44999695,
            216.30999756,
            206.0
          ]
        },
        "risk_pct": 10.6
      },
      "analysis": "It is coming off a base, 14% below its one-year high, so there is room to run. RSI has turned up through its signal line. Trade idea: entry $228.0300, stop $203.9400, target $260.0400 (1.33:1) \u2014 then trail it.",
      "sector_count": 0
    }
  ]
}