{
  "market": "scalp",
  "label": "SCALP",
  "setup_type": "scalp",
  "currency": "USD",
  "currency_symbol": "$",
  "timezone": "UTC",
  "tz_label": "UTC",
  "generated_at": "2026-06-20T08:33:45+00:00",
  "timeframe": "1h",
  "scanned": 34,
  "universe_size": 64,
  "score_max": 10,
  "brokerage": 20,
  "position_size": 1000,
  "leverage": 5,
  "max_daily_trades": 5,
  "pulse": [],
  "results": [
    {
      "symbol": "QCOM",
      "name": "Qualcomm",
      "sector": "Technology",
      "asset_type": "nasdaq",
      "dir": "LONG",
      "grade": "A+",
      "score": 9,
      "score_max": 10,
      "chips": [
        "SQUEEZE FIRED",
        "MOMENTUM ALIGNED",
        "MOMENTUM ACCELERATING",
        "SUPPORT @ 221.0000",
        "VOLUME EXPANSION"
      ],
      "weekly": true,
      "low_rr": false,
      "rr_text": "2.0:1",
      "target_2r": false,
      "liquidity": "LIQUID",
      "price": 226.07000732,
      "y_close": 226.07000732,
      "open": 226.07000732,
      "open_pct": 0.0,
      "current_pct": 0.0,
      "day_pct": 0.0,
      "entry": 226.07000732,
      "stop": 218.93114291,
      "target": 240.34773613,
      "rr": 2.0,
      "trail": 218.93114291,
      "stop_pct": 3.2,
      "p2_pct": 6.3,
      "target_basis": "atr",
      "spark": [
        211.69000244,
        211.66999817,
        220.66000366,
        222.0,
        222.28990173,
        221.75010681,
        221.17999268,
        220.44000244,
        220.78999329,
        226.47000122,
        219.22000122,
        220.77999878,
        219.47000122,
        218.8999939,
        218.49499512,
        213.82000732,
        218.57000732,
        217.36999512,
        218.83000183,
        218.23500061,
        215.53500366,
        215.50999451,
        212.99000549,
        222.44500732,
        222.03999329,
        221.98500061,
        225.63000488,
        229.09500122,
        226.57499695,
        226.07000732
      ],
      "trend": "green",
      "turnover": 0,
      "detail": {
        "setup_type": "scalp",
        "entry": 226.070007,
        "stop": 218.931143,
        "target": 240.347736,
        "stop_pct": 3.16,
        "target_pct": 6.32,
        "notional": 5000,
        "units": 22,
        "risk_dollars": 157.06,
        "reward_dollars": 314.11,
        "brokerage_rt": 40,
        "net_loss": 197.06,
        "net_profit": 274.11,
        "eff_rr": 1.39,
        "sq_state": "FIRED",
        "mom_val": 6.627787,
        "nearest_support": 221.0,
        "support_pct": -2.24,
        "nearest_resistance": 226.460007,
        "resistance_pct": 0.17,
        "bb_upper": 228.496045,
        "bb_mid": 220.078251,
        "bb_lower": 211.660456,
        "kc_upper": 227.237098,
        "kc_lower": 212.919404,
        "atr": 4.75924294,
        "swing_high": 231.190002,
        "swing_high_pct": 2.26,
        "swing_low": 190.100006,
        "swing_low_pct": -15.91,
        "volume_ratio": 1.57,
        "volume_expanding": true,
        "volume_today": 3086027,
        "volume_avg": 1965318
      },
      "analysis": "QCOM (NASDAQ) long scalp \u2014 squeeze fired. momentum \u25b2 +6.6278. Support $221.0000. Stop $218.9311 (3.2% risk), target $240.3477 (2.0:1 R:R)."
    },
    {
      "symbol": "ETH",
      "name": "Ethereum",
      "sector": "Crypto",
      "asset_type": "crypto",
      "dir": "LONG",
      "grade": "A+",
      "score": 9,
      "score_max": 10,
      "chips": [
        "SQUEEZE FIRED",
        "MOMENTUM ALIGNED",
        "MOMENTUM ACCELERATING",
        "SUPPORT @ 1721.4000",
        "VOLUME EXPANSION"
      ],
      "weekly": true,
      "low_rr": false,
      "rr_text": "2.0:1",
      "target_2r": false,
      "liquidity": "LIQUID",
      "price": 1722.25,
      "y_close": 1722.25,
      "open": 1722.25,
      "open_pct": 0.0,
      "current_pct": 0.0,
      "day_pct": 0.0,
      "entry": 1722.25,
      "stop": 1707.53559285,
      "target": 1751.67881431,
      "rr": 2.0,
      "trail": 1707.53559285,
      "stop_pct": 0.9,
      "p2_pct": 1.7,
      "target_basis": "atr",
      "spark": [
        1695.60998535,
        1688.09997559,
        1695.88000488,
        1698.69995117,
        1694.06994629,
        1695.79003906,
        1687.55004883,
        1691.39001465,
        1690.07995605,
        1693.59997559,
        1701.5300293,
        1705.40002441,
        1706.08996582,
        1694.92004395,
        1703.31005859,
        1701.22998047,
        1699.39001465,
        1706.9699707,
        1700.19995117,
        1705.66003418,
        1709.41003418,
        1707.10998535,
        1708.42004395,
        1703.11999512,
        1706.45996094,
        1711.85998535,
        1724.27001953,
        1725.97998047,
        1724.19995117,
        1722.25
      ],
      "trend": "green",
      "turnover": 0,
      "detail": {
        "setup_type": "scalp",
        "entry": 1722.25,
        "stop": 1707.535593,
        "target": 1751.678814,
        "stop_pct": 0.85,
        "target_pct": 1.71,
        "notional": 5000,
        "units": 2,
        "risk_dollars": 29.43,
        "reward_dollars": 58.86,
        "brokerage_rt": 40,
        "net_loss": 69.43,
        "net_profit": 18.86,
        "eff_rr": 0.27,
        "sq_state": "FIRED",
        "mom_val": 18.526512,
        "nearest_support": 1721.400024,
        "support_pct": -0.05,
        "nearest_resistance": 1729.859985,
        "resistance_pct": 0.44,
        "bb_upper": 1725.865853,
        "bb_mid": 1708.389001,
        "bb_lower": 1690.91215,
        "kc_upper": 1724.53909,
        "kc_lower": 1692.238913,
        "atr": 9.80960477,
        "swing_high": 1761.5,
        "swing_high_pct": 2.28,
        "swing_low": 1669.569946,
        "swing_low_pct": -3.06,
        "volume_ratio": 3.73,
        "volume_expanding": true,
        "volume_today": 133827072,
        "volume_avg": 35922176
      },
      "analysis": "ETH (CRYPTO) long scalp \u2014 squeeze fired. momentum \u25b2 +18.5265. Support $1721.4000. Stop $1707.5356 (0.9% risk), target $1751.6788 (2.0:1 R:R)."
    },
    {
      "symbol": "ORCL",
      "name": "Oracle",
      "sector": "Technology",
      "asset_type": "nasdaq",
      "dir": "SHORT",
      "grade": "A",
      "score": 7,
      "score_max": 10,
      "chips": [
        "SQUEEZE FIRED",
        "MOMENTUM ALIGNED",
        "RESISTANCE @ 184.7000"
      ],
      "weekly": true,
      "low_rr": false,
      "rr_text": "2.0:1",
      "target_2r": false,
      "liquidity": "LIQUID",
      "price": 184.30999756,
      "y_close": 184.30999756,
      "open": 184.30999756,
      "open_pct": 0.0,
      "current_pct": 0.0,
      "day_pct": 0.0,
      "entry": 184.30999756,
      "stop": 188.73206751,
      "target": 175.46585766,
      "rr": 2.0,
      "trail": 188.73206751,
      "stop_pct": 2.4,
      "p2_pct": 4.8,
      "target_basis": "atr",
      "spark": [
        182.96000671,
        184.11999512,
        193.67999268,
        194.26499939,
        194.99859619,
        193.67500305,
        193.07000732,
        192.24499512,
        192.69000244,
        188.88999939,
        189.83000183,
        189.77000427,
        189.04499817,
        189.77999878,
        189.6000061,
        188.375,
        188.91000366,
        188.11999512,
        189.16499329,
        189.3500061,
        186.72250366,
        184.83500671,
        183.50999451,
        181.50999451,
        184.30999756,
        184.94500732,
        186.70500183,
        185.57499695,
        184.58999634,
        184.30999756
      ],
      "trend": "blue",
      "turnover": 0,
      "detail": {
        "setup_type": "scalp",
        "entry": 184.309998,
        "stop": 188.732068,
        "target": 175.465858,
        "stop_pct": 2.4,
        "target_pct": 4.8,
        "notional": 5000,
        "units": 27,
        "risk_dollars": 119.4,
        "reward_dollars": 238.79,
        "brokerage_rt": 40,
        "net_loss": 159.4,
        "net_profit": 198.79,
        "eff_rr": 1.25,
        "sq_state": "FIRED",
        "mom_val": -2.455644,
        "nearest_support": 180.520905,
        "support_pct": -2.06,
        "nearest_resistance": 184.699997,
        "resistance_pct": 0.21,
        "bb_upper": 191.948001,
        "bb_mid": 186.947875,
        "bb_lower": 181.94775,
        "kc_upper": 191.743764,
        "kc_lower": 182.151987,
        "atr": 2.94804663,
        "swing_high": 220.5,
        "swing_high_pct": 19.64,
        "swing_low": 175.279999,
        "swing_low_pct": -4.9,
        "volume_ratio": 1.1,
        "volume_expanding": false,
        "volume_today": 2468658,
        "volume_avg": 2248865
      },
      "analysis": "ORCL (NASDAQ) short scalp \u2014 squeeze fired. momentum \u25bc -2.4556. Resistance $184.7000. Stop $188.7321 (2.4% risk), target $175.4659 (2.0:1 R:R)."
    },
    {
      "symbol": "US30",
      "name": "Dow Jones 30",
      "sector": "Index",
      "asset_type": "index",
      "dir": "SHORT",
      "grade": "A",
      "score": 7,
      "score_max": 10,
      "chips": [
        "SQUEEZE FIRED",
        "MOMENTUM ALIGNED",
        "RESISTANCE @ 51964.0000"
      ],
      "weekly": true,
      "low_rr": false,
      "rr_text": "2.0:1",
      "target_2r": false,
      "liquidity": "LIQUID",
      "price": 51875.0,
      "y_close": 51875.0,
      "open": 51875.0,
      "open_pct": 0.0,
      "current_pct": 0.0,
      "day_pct": 0.0,
      "entry": 51875.0,
      "stop": 52035.52326533,
      "target": 51553.95346935,
      "rr": 2.0,
      "trail": 52035.52326533,
      "stop_pct": 0.3,
      "p2_pct": 0.6,
      "target_basis": "atr",
      "spark": [
        52049.0,
        52071.0,
        52175.0,
        52204.0,
        52228.0,
        52241.0,
        52242.0,
        52192.0,
        52183.0,
        52249.0,
        52234.0,
        52150.0,
        52248.0,
        52155.0,
        52048.0,
        52208.0,
        52152.0,
        52212.0,
        52083.0,
        52064.0,
        52076.0,
        52037.0,
        51975.0,
        52053.0,
        51974.0,
        52006.0,
        51968.0,
        51908.0,
        51888.0,
        51875.0
      ],
      "trend": "blue",
      "turnover": 0,
      "detail": {
        "setup_type": "scalp",
        "entry": 51875.0,
        "stop": 52035.523265,
        "target": 51553.953469,
        "stop_pct": 0.31,
        "target_pct": 0.62,
        "notional": 5000,
        "units": 0,
        "risk_dollars": 0.0,
        "reward_dollars": 0.0,
        "brokerage_rt": 40,
        "net_loss": 40.0,
        "net_profit": -40.0,
        "eff_rr": -1.0,
        "sq_state": "FIRED",
        "mom_val": -222.209936,
        "nearest_support": 51839.0,
        "support_pct": -0.07,
        "nearest_resistance": 51964.0,
        "resistance_pct": 0.17,
        "bb_upper": 52289.308676,
        "bb_mid": 52065.7,
        "bb_lower": 51842.091324,
        "kc_upper": 52231.694873,
        "kc_lower": 51899.705127,
        "atr": 107.01551022,
        "swing_high": 52734.0,
        "swing_high_pct": 1.66,
        "swing_low": 51839.0,
        "swing_low_pct": -0.07,
        "volume_ratio": 0.1,
        "volume_expanding": false,
        "volume_today": 422,
        "volume_avg": 4261
      },
      "analysis": "US30 (INDEX) short scalp \u2014 squeeze fired. momentum \u25bc -222.2099. Resistance $51964.0000. Stop $52035.5233 (0.3% risk), target $51553.9535 (2.0:1 R:R)."
    },
    {
      "symbol": "XRP",
      "name": "XRP",
      "sector": "Crypto",
      "asset_type": "crypto",
      "dir": "LONG",
      "grade": "A",
      "score": 7,
      "score_max": 10,
      "chips": [
        "SQUEEZE FIRED",
        "MOMENTUM ALIGNED",
        "SUPPORT @ 1.1425"
      ],
      "weekly": true,
      "low_rr": false,
      "rr_text": "2.0:1",
      "target_2r": false,
      "liquidity": "LIQUID",
      "price": 1.14569998,
      "y_close": 1.14569998,
      "open": 1.14569998,
      "open_pct": 0.0,
      "current_pct": 0.0,
      "day_pct": 0.0,
      "entry": 1.14569998,
      "stop": 1.13527835,
      "target": 1.16654324,
      "rr": 2.0,
      "trail": 1.13527835,
      "stop_pct": 0.9,
      "p2_pct": 1.8,
      "target_basis": "atr",
      "spark": [
        1.13789999,
        1.12619996,
        1.13240004,
        1.13300002,
        1.12419999,
        1.12549996,
        1.12380004,
        1.1243,
        1.12619996,
        1.13039994,
        1.13870001,
        1.13559997,
        1.13590002,
        1.1293,
        1.13520002,
        1.13160002,
        1.13039994,
        1.1336,
        1.12880003,
        1.13310003,
        1.13489997,
        1.13639998,
        1.14100003,
        1.13800001,
        1.13890004,
        1.14310002,
        1.14680004,
        1.14890003,
        1.14629996,
        1.14569998
      ],
      "trend": "blue",
      "turnover": 0,
      "detail": {
        "setup_type": "scalp",
        "entry": 1.1457,
        "stop": 1.135278,
        "target": 1.166543,
        "stop_pct": 0.91,
        "target_pct": 1.82,
        "notional": 5000,
        "units": 4364,
        "risk_dollars": 45.48,
        "reward_dollars": 90.96,
        "brokerage_rt": 40,
        "net_loss": 85.48,
        "net_profit": 50.96,
        "eff_rr": 0.6,
        "sq_state": "FIRED",
        "mom_val": 0.012584,
        "nearest_support": 1.1425,
        "support_pct": -0.28,
        "nearest_resistance": 1.1518,
        "resistance_pct": 0.53,
        "bb_upper": 1.14936,
        "bb_mid": 1.13761,
        "bb_lower": 1.12586,
        "kc_upper": 1.149013,
        "kc_lower": 1.126207,
        "atr": 0.00694775,
        "swing_high": 1.1912,
        "swing_high_pct": 3.97,
        "swing_low": 1.1191,
        "swing_low_pct": -2.32,
        "volume_ratio": 0.0,
        "volume_expanding": false,
        "volume_today": 0,
        "volume_avg": 544550
      },
      "analysis": "XRP (CRYPTO) long scalp \u2014 squeeze fired. momentum \u25b2 +0.0126. Support $1.1425. Stop $1.1353 (0.9% risk), target $1.1665 (2.0:1 R:R)."
    },
    {
      "symbol": "DOT",
      "name": "Polkadot",
      "sector": "Crypto",
      "asset_type": "crypto",
      "dir": "LONG",
      "grade": "A",
      "score": 7,
      "score_max": 10,
      "chips": [
        "SQUEEZE BUILDING",
        "MOMENTUM ALIGNED",
        "MOMENTUM ACCELERATING",
        "SUPPORT @ 0.9540",
        "VOLUME EXPANSION"
      ],
      "weekly": false,
      "low_rr": false,
      "rr_text": "2.0:1",
      "target_2r": false,
      "liquidity": "LIQUID",
      "price": 0.963,
      "y_close": 0.963,
      "open": 0.963,
      "open_pct": 0.0,
      "current_pct": 0.0,
      "day_pct": 0.0,
      "entry": 0.963,
      "stop": 0.95140119,
      "target": 0.98619762,
      "rr": 2.0,
      "trail": 0.95140119,
      "stop_pct": 1.2,
      "p2_pct": 2.4,
      "target_basis": "atr",
      "spark": [
        0.96600002,
        0.954,
        0.96200001,
        0.96100003,
        0.95300001,
        0.95599997,
        0.95300001,
        0.95200002,
        0.94999999,
        0.95599997,
        0.96700001,
        0.96399999,
        0.96700001,
        0.954,
        0.96100003,
        0.954,
        0.95200002,
        0.95899999,
        0.95200002,
        0.95599997,
        0.96100003,
        0.95999998,
        0.95999998,
        0.95499998,
        0.95599997,
        0.96100003,
        0.96600002,
        0.96600002,
        0.96200001,
        0.963
      ],
      "trend": "blue",
      "turnover": 0,
      "detail": {
        "setup_type": "scalp",
        "entry": 0.963,
        "stop": 0.951401,
        "target": 0.986198,
        "stop_pct": 1.2,
        "target_pct": 2.41,
        "notional": 5000,
        "units": 5192,
        "risk_dollars": 60.22,
        "reward_dollars": 120.44,
        "brokerage_rt": 40,
        "net_loss": 100.22,
        "net_profit": 80.44,
        "eff_rr": 0.8,
        "sq_state": "BUILDING",
        "mom_val": 0.005546,
        "nearest_support": 0.954,
        "support_pct": -0.93,
        "nearest_resistance": 0.965,
        "resistance_pct": 0.21,
        "bb_upper": 0.969383,
        "bb_mid": 0.9598,
        "bb_lower": 0.950217,
        "kc_upper": 0.972408,
        "kc_lower": 0.947192,
        "atr": 0.00773254,
        "swing_high": 1.009,
        "swing_high_pct": 4.78,
        "swing_low": 0.94,
        "swing_low_pct": -2.39,
        "volume_ratio": 5.14,
        "volume_expanding": true,
        "volume_today": 462684,
        "volume_avg": 89931
      },
      "analysis": "DOT (CRYPTO) long scalp \u2014 squeeze building (coiling). momentum \u25b2 +0.0055. Support $0.9540. Stop $0.9514 (1.2% risk), target $0.9862 (2.0:1 R:R)."
    },
    {
      "symbol": "AMD",
      "name": "AMD",
      "sector": "Technology",
      "asset_type": "nasdaq",
      "dir": "LONG",
      "grade": "B",
      "score": 6,
      "score_max": 10,
      "chips": [
        "SQUEEZE BUILDING",
        "MOMENTUM ALIGNED",
        "MOMENTUM ACCELERATING",
        "SUPPORT @ 529.8500"
      ],
      "weekly": false,
      "low_rr": false,
      "rr_text": "2.0:1",
      "target_2r": false,
      "liquidity": "LIQUID",
      "price": 536.83001709,
      "y_close": 536.83001709,
      "open": 536.83001709,
      "open_pct": 0.0,
      "current_pct": 0.0,
      "day_pct": 0.0,
      "entry": 536.83001709,
      "stop": 521.85957825,
      "target": 566.77089477,
      "rr": 2.0,
      "trail": 521.85957825,
      "stop_pct": 2.8,
      "p2_pct": 5.6,
      "target_basis": "atr",
      "spark": [
        512.70001221,
        511.11999512,
        550.81988525,
        549.53997803,
        551.03997803,
        548.48498535,
        547.02502441,
        545.45001221,
        547.26000977,
        528.29998779,
        522.17498779,
        522.90002441,
        520.69000244,
        518.89080811,
        517.5,
        507.29000854,
        521.42498779,
        523.05499268,
        522.79498291,
        525.1550293,
        518.83001709,
        517.0300293,
        512.05999756,
        531.25,
        531.58666992,
        534.58502197,
        533.83001709,
        533.24987793,
        531.07000732,
        536.83001709
      ],
      "trend": "blue",
      "turnover": 0,
      "detail": {
        "setup_type": "scalp",
        "entry": 536.830017,
        "stop": 521.859578,
        "target": 566.770895,
        "stop_pct": 2.79,
        "target_pct": 5.58,
        "notional": 5000,
        "units": 9,
        "risk_dollars": 134.73,
        "reward_dollars": 269.47,
        "brokerage_rt": 40,
        "net_loss": 174.73,
        "net_profit": 229.47,
        "eff_rr": 1.31,
        "sq_state": "BUILDING",
        "mom_val": 11.510177,
        "nearest_support": 529.849976,
        "support_pct": -1.3,
        "nearest_resistance": 539.619873,
        "resistance_pct": 0.52,
        "bb_upper": 539.66598,
        "bb_mid": 524.109874,
        "bb_lower": 508.553768,
        "kc_upper": 539.704341,
        "kc_lower": 508.515407,
        "atr": 9.98029256,
        "swing_high": 558.369995,
        "swing_high_pct": 4.01,
        "swing_low": 437.230011,
        "swing_low_pct": -18.55,
        "volume_ratio": 1.05,
        "volume_expanding": false,
        "volume_today": 3598999,
        "volume_avg": 3420458
      },
      "analysis": "AMD (NASDAQ) long scalp \u2014 squeeze building (coiling). momentum \u25b2 +11.5102. Support $529.8500. Stop $521.8596 (2.8% risk), target $566.7709 (2.0:1 R:R)."
    },
    {
      "symbol": "AVGO",
      "name": "Broadcom",
      "sector": "Technology",
      "asset_type": "nasdaq",
      "dir": "LONG",
      "grade": "B",
      "score": 6,
      "score_max": 10,
      "chips": [
        "MOMENTUM ALIGNED",
        "MOMENTUM ACCELERATING",
        "SUPPORT @ 407.8500",
        "VOLUME EXPANSION"
      ],
      "weekly": false,
      "low_rr": false,
      "rr_text": "2.0:1",
      "target_2r": false,
      "liquidity": "LIQUID",
      "price": 410.79000854,
      "y_close": 410.79000854,
      "open": 410.79000854,
      "open_pct": 0.0,
      "current_pct": 0.0,
      "day_pct": 0.0,
      "entry": 410.79000854,
      "stop": 402.27736867,
      "target": 427.81528827,
      "rr": 2.0,
      "trail": 402.27736867,
      "stop_pct": 2.1,
      "p2_pct": 4.1,
      "target_basis": "atr",
      "spark": [
        381.11999512,
        381.85998535,
        390.53500366,
        392.34500122,
        393.02999878,
        393.04000854,
        393.72000122,
        394.05999756,
        394.13000488,
        382.42999268,
        379.81500244,
        378.95498657,
        379.39001465,
        381.21499634,
        379.69000244,
        376.83999634,
        397.32000732,
        397.32000732,
        398.38000488,
        396.67498779,
        394.88500977,
        393.27999878,
        392.8999939,
        407.79501343,
        408.79998779,
        408.58999634,
        407.28500366,
        407.39001465,
        409.20001221,
        410.79000854
      ],
      "trend": "blue",
      "turnover": 0,
      "detail": {
        "setup_type": "scalp",
        "entry": 410.790009,
        "stop": 402.277369,
        "target": 427.815288,
        "stop_pct": 2.07,
        "target_pct": 4.14,
        "notional": 5000,
        "units": 12,
        "risk_dollars": 102.15,
        "reward_dollars": 204.3,
        "brokerage_rt": 40,
        "net_loss": 142.15,
        "net_profit": 164.3,
        "eff_rr": 1.16,
        "sq_state": "RELEASED",
        "mom_val": 16.345592,
        "nearest_support": 407.850006,
        "support_pct": -0.72,
        "nearest_resistance": 412.480011,
        "resistance_pct": 0.41,
        "bb_upper": 419.033975,
        "bb_mid": 395.325752,
        "bb_lower": 371.61753,
        "kc_upper": 404.300165,
        "kc_lower": 386.351339,
        "atr": 5.67509324,
        "swing_high": 412.700012,
        "swing_high_pct": 0.46,
        "swing_low": 370.329987,
        "swing_low_pct": -9.85,
        "volume_ratio": 1.42,
        "volume_expanding": true,
        "volume_today": 4901575,
        "volume_avg": 3460989
      },
      "analysis": "AVGO (NASDAQ) long scalp \u2014 squeeze released. momentum \u25b2 +16.3456. Support $407.8500. Stop $402.2774 (2.1% risk), target $427.8153 (2.0:1 R:R)."
    },
    {
      "symbol": "BTC",
      "name": "Bitcoin",
      "sector": "Crypto",
      "asset_type": "crypto",
      "dir": "LONG",
      "grade": "B",
      "score": 6,
      "score_max": 10,
      "chips": [
        "SQUEEZE BUILDING",
        "MOMENTUM ALIGNED",
        "SUPPORT @ 63350.0117",
        "VOLUME EXPANSION"
      ],
      "weekly": false,
      "low_rr": false,
      "rr_text": "2.0:1",
      "target_2r": false,
      "liquidity": "LIQUID",
      "price": 63414.890625,
      "y_close": 63414.890625,
      "open": 63414.890625,
      "open_pct": 0.0,
      "current_pct": 0.0,
      "day_pct": 0.0,
      "entry": 63414.890625,
      "stop": 62982.47304621,
      "target": 64279.72578258,
      "rr": 2.0,
      "trail": 62982.47304621,
      "stop_pct": 0.7,
      "p2_pct": 1.4,
      "target_basis": "atr",
      "spark": [
        62702.0703125,
        62387.140625,
        62675.80859375,
        62829.3203125,
        62561.2109375,
        62529.421875,
        62317.12109375,
        62466.30859375,
        62570.51953125,
        62768.44140625,
        63151.171875,
        63145.390625,
        63147.37109375,
        62911.5390625,
        63143.62109375,
        63049.5390625,
        62968.94140625,
        63190.23828125,
        63015.1015625,
        63256.94140625,
        63475.6484375,
        63464.0,
        63529.73828125,
        63279.62890625,
        63424.51953125,
        63520.01953125,
        63613.05078125,
        63678.421875,
        63582.55859375,
        63414.890625
      ],
      "trend": "blue",
      "turnover": 0,
      "detail": {
        "setup_type": "scalp",
        "entry": 63414.890625,
        "stop": 62982.473046,
        "target": 64279.725783,
        "stop_pct": 0.68,
        "target_pct": 1.36,
        "notional": 5000,
        "units": 0,
        "risk_dollars": 0.0,
        "reward_dollars": 0.0,
        "brokerage_rt": 40,
        "net_loss": 40.0,
        "net_profit": -40.0,
        "eff_rr": -1.0,
        "sq_state": "BUILDING",
        "mom_val": 408.048369,
        "nearest_support": 63350.011719,
        "support_pct": -0.1,
        "nearest_resistance": 63632.0,
        "resistance_pct": 0.34,
        "bb_upper": 63750.031174,
        "bb_mid": 63298.116602,
        "bb_lower": 62846.202029,
        "kc_upper": 63768.088569,
        "kc_lower": 62828.144634,
        "atr": 288.27838586,
        "swing_high": 64751.921875,
        "swing_high_pct": 2.11,
        "swing_low": 62190.0,
        "swing_low_pct": -1.93,
        "volume_ratio": 11.71,
        "volume_expanding": true,
        "volume_today": 121407488,
        "volume_avg": 10364620
      },
      "analysis": "BTC (CRYPTO) long scalp \u2014 squeeze building (coiling). momentum \u25b2 +408.0484. Support $63350.0117. Stop $62982.4730 (0.7% risk), target $64279.7258 (2.0:1 R:R)."
    },
    {
      "symbol": "DOGE",
      "name": "Dogecoin",
      "sector": "Crypto",
      "asset_type": "crypto",
      "dir": "LONG",
      "grade": "B",
      "score": 6,
      "score_max": 10,
      "chips": [
        "SQUEEZE BUILDING",
        "MOMENTUM ALIGNED",
        "SUPPORT @ 0.0838",
        "VOLUME EXPANSION"
      ],
      "weekly": false,
      "low_rr": false,
      "rr_text": "2.0:1",
      "target_2r": false,
      "liquidity": "LIQUID",
      "price": 0.08385,
      "y_close": 0.08385,
      "open": 0.08385,
      "open_pct": 0.0,
      "current_pct": 0.0,
      "day_pct": 0.0,
      "entry": 0.08385,
      "stop": 0.08313341,
      "target": 0.08528318,
      "rr": 2.0,
      "trail": 0.08313341,
      "stop_pct": 0.9,
      "p2_pct": 1.7,
      "target_basis": "atr",
      "spark": [
        0.08281,
        0.08216,
        0.08255,
        0.08268,
        0.08226,
        0.08245,
        0.08219,
        0.08225,
        0.08233,
        0.08261,
        0.08317,
        0.08304,
        0.08311,
        0.0828,
        0.08328,
        0.08307,
        0.08283,
        0.08317,
        0.08277,
        0.08317,
        0.08347,
        0.0834,
        0.08341,
        0.08298,
        0.08318,
        0.08341,
        0.08388,
        0.08413,
        0.08401,
        0.08385
      ],
      "trend": "blue",
      "turnover": 0,
      "detail": {
        "setup_type": "scalp",
        "entry": 0.08385,
        "stop": 0.083133,
        "target": 0.085283,
        "stop_pct": 0.85,
        "target_pct": 1.71,
        "notional": 5000,
        "units": 59630,
        "risk_dollars": 42.73,
        "reward_dollars": 85.46,
        "brokerage_rt": 40,
        "net_loss": 82.73,
        "net_profit": 45.46,
        "eff_rr": 0.55,
        "sq_state": "BUILDING",
        "mom_val": 0.000809,
        "nearest_support": 0.08383,
        "support_pct": -0.02,
        "nearest_resistance": 0.08387,
        "resistance_pct": 0.02,
        "bb_upper": 0.084077,
        "bb_mid": 0.083306,
        "bb_lower": 0.082536,
        "kc_upper": 0.084084,
        "kc_lower": 0.082529,
        "atr": 0.00047773,
        "swing_high": 0.08649,
        "swing_high_pct": 3.15,
        "swing_low": 0.08176,
        "swing_low_pct": -2.49,
        "volume_ratio": 3.45,
        "volume_expanding": true,
        "volume_today": 5981600,
        "volume_avg": 1732430
      },
      "analysis": "DOGE (CRYPTO) long scalp \u2014 squeeze building (coiling). momentum \u25b2 +0.0008. Support $0.0838. Stop $0.0831 (0.9% risk), target $0.0853 (2.0:1 R:R)."
    },
    {
      "symbol": "BCH",
      "name": "Bitcoin Cash",
      "sector": "Crypto",
      "asset_type": "crypto",
      "dir": "LONG",
      "grade": "B",
      "score": 6,
      "score_max": 10,
      "chips": [
        "SQUEEZE BUILDING",
        "MOMENTUM ALIGNED",
        "SUPPORT @ 198.8500",
        "VOLUME EXPANSION"
      ],
      "weekly": false,
      "low_rr": false,
      "rr_text": "2.0:1",
      "target_2r": false,
      "liquidity": "LIQUID",
      "price": 198.8500061,
      "y_close": 198.8500061,
      "open": 198.8500061,
      "open_pct": 0.0,
      "current_pct": 0.0,
      "day_pct": 0.0,
      "entry": 198.8500061,
      "stop": 196.29573062,
      "target": 203.95855706,
      "rr": 2.0,
      "trail": 196.29573062,
      "stop_pct": 1.3,
      "p2_pct": 2.6,
      "target_basis": "atr",
      "spark": [
        194.61000061,
        193.55000305,
        195.03999329,
        195.07000732,
        193.74000549,
        193.66000366,
        193.63000488,
        194.82000732,
        195.07000732,
        196.0,
        197.80000305,
        196.92999268,
        196.77999878,
        196.07000732,
        197.6000061,
        197.66000366,
        197.25,
        198.1000061,
        196.80000305,
        197.47000122,
        198.47000122,
        198.0,
        198.16000366,
        197.22000122,
        197.36000061,
        198.0,
        199.02000427,
        199.46000671,
        199.61000061,
        198.8500061
      ],
      "trend": "blue",
      "turnover": 0,
      "detail": {
        "setup_type": "scalp",
        "entry": 198.850006,
        "stop": 196.295731,
        "target": 203.958557,
        "stop_pct": 1.28,
        "target_pct": 2.57,
        "notional": 5000,
        "units": 25,
        "risk_dollars": 63.86,
        "reward_dollars": 127.71,
        "brokerage_rt": 40,
        "net_loss": 103.86,
        "net_profit": 87.71,
        "eff_rr": 0.84,
        "sq_state": "BUILDING",
        "mom_val": 1.590247,
        "nearest_support": 198.850006,
        "support_pct": -0.0,
        "nearest_resistance": 199.589996,
        "resistance_pct": 0.37,
        "bb_upper": 199.627373,
        "bb_mid": 197.830502,
        "bb_lower": 196.033631,
        "kc_upper": 200.570658,
        "kc_lower": 195.090347,
        "atr": 1.70285032,
        "swing_high": 215.089996,
        "swing_high_pct": 8.17,
        "swing_low": 192.759995,
        "swing_low_pct": -3.06,
        "volume_ratio": 1.91,
        "volume_expanding": true,
        "volume_today": 430944,
        "volume_avg": 225242
      },
      "analysis": "BCH (CRYPTO) long scalp \u2014 squeeze building (coiling). momentum \u25b2 +1.5902. Support $198.8500. Stop $196.2957 (1.3% risk), target $203.9586 (2.0:1 R:R)."
    },
    {
      "symbol": "NVDA",
      "name": "NVIDIA",
      "sector": "Technology",
      "asset_type": "nasdaq",
      "dir": "LONG",
      "grade": "B",
      "score": 5,
      "score_max": 10,
      "chips": [
        "MOMENTUM ALIGNED",
        "MOMENTUM ACCELERATING",
        "SUPPORT @ 208.2800"
      ],
      "weekly": false,
      "low_rr": false,
      "rr_text": "2.0:1",
      "target_2r": false,
      "liquidity": "LIQUID",
      "price": 210.22999573,
      "y_close": 210.22999573,
      "open": 210.22999573,
      "open_pct": 0.0,
      "current_pct": 0.0,
      "day_pct": 0.0,
      "entry": 210.22999573,
      "stop": 207.28091892,
      "target": 216.12814935,
      "rr": 2.0,
      "trail": 207.28091892,
      "stop_pct": 1.4,
      "p2_pct": 2.8,
      "target_basis": "atr",
      "spark": [
        204.75,
        205.13000488,
        209.39500427,
        211.16499329,
        212.34500122,
        212.52999878,
        211.94000244,
        211.66000366,
        212.46000671,
        209.07000732,
        209.1499939,
        209.28500366,
        209.1000061,
        209.45010376,
        208.93009949,
        207.28999329,
        207.89439392,
        206.44999695,
        207.42999268,
        207.36399841,
        205.96499634,
        204.72000122,
        204.67799377,
        209.13009644,
        208.88499451,
        209.98500061,
        210.05999756,
        210.19500732,
        209.85499573,
        210.22999573
      ],
      "trend": "blue",
      "turnover": 0,
      "detail": {
        "setup_type": "scalp",
        "entry": 210.229996,
        "stop": 207.280919,
        "target": 216.128149,
        "stop_pct": 1.4,
        "target_pct": 2.81,
        "notional": 5000,
        "units": 23,
        "risk_dollars": 67.83,
        "reward_dollars": 135.66,
        "brokerage_rt": 40,
        "net_loss": 107.83,
        "net_profit": 95.66,
        "eff_rr": 0.89,
        "sq_state": "RELEASED",
        "mom_val": 2.687705,
        "nearest_support": 208.279999,
        "support_pct": -0.93,
        "nearest_resistance": 211.389999,
        "resistance_pct": 0.55,
        "bb_upper": 211.719412,
        "bb_mid": 208.302333,
        "bb_lower": 204.885254,
        "kc_upper": 211.404916,
        "kc_lower": 205.19975,
        "atr": 1.96605121,
        "swing_high": 212.710693,
        "swing_high_pct": 1.18,
        "swing_low": 199.339996,
        "swing_low_pct": -5.18,
        "volume_ratio": 1.02,
        "volume_expanding": false,
        "volume_today": 15910016,
        "volume_avg": 15535954
      },
      "analysis": "NVDA (NASDAQ) long scalp \u2014 squeeze released. momentum \u25b2 +2.6877. Support $208.2800. Stop $207.2809 (1.4% risk), target $216.1281 (2.0:1 R:R)."
    },
    {
      "symbol": "AMZN",
      "name": "Amazon",
      "sector": "Consumer Disc",
      "asset_type": "nasdaq",
      "dir": "LONG",
      "grade": "B",
      "score": 5,
      "score_max": 10,
      "chips": [
        "MOMENTUM ALIGNED",
        "MOMENTUM ACCELERATING",
        "SUPPORT @ 243.3300"
      ],
      "weekly": false,
      "low_rr": false,
      "rr_text": "2.0:1",
      "target_2r": false,
      "liquidity": "LIQUID",
      "price": 244.35249329,
      "y_close": 244.35249329,
      "open": 244.35249329,
      "open_pct": 0.0,
      "current_pct": 0.0,
      "day_pct": 0.0,
      "entry": 244.35249329,
      "stop": 240.90939933,
      "target": 251.2386812,
      "rr": 2.0,
      "trail": 240.90939933,
      "stop_pct": 1.4,
      "p2_pct": 2.8,
      "target_basis": "atr",
      "spark": [
        237.86999512,
        238.52999878,
        246.11999512,
        246.08999634,
        246.71000671,
        246.7749939,
        246.15499878,
        245.84500122,
        246.1000061,
        246.80999756,
        248.72819519,
        247.13999939,
        245.83000183,
        246.21000671,
        246.1000061,
        246.07000732,
        242.03999329,
        240.33799744,
        240.63999939,
        239.99000549,
        239.30499268,
        237.44500732,
        237.44000244,
        239.39500427,
        242.34500122,
        243.4499054,
        245.28500366,
        242.94000244,
        243.07000732,
        244.35249329
      ],
      "trend": "blue",
      "turnover": 0,
      "detail": {
        "setup_type": "scalp",
        "entry": 244.352493,
        "stop": 240.909399,
        "target": 251.238681,
        "stop_pct": 1.41,
        "target_pct": 2.82,
        "notional": 5000,
        "units": 20,
        "risk_dollars": 68.86,
        "reward_dollars": 137.72,
        "brokerage_rt": 40,
        "net_loss": 108.86,
        "net_profit": 97.72,
        "eff_rr": 0.9,
        "sq_state": "RELEASED",
        "mom_val": 1.485374,
        "nearest_support": 243.330002,
        "support_pct": -0.42,
        "nearest_resistance": 245.451096,
        "resistance_pct": 0.45,
        "bb_upper": 249.322386,
        "bb_mid": 242.905682,
        "bb_lower": 236.488977,
        "kc_upper": 246.37785,
        "kc_lower": 239.433513,
        "atr": 2.29539597,
        "swing_high": 250.429993,
        "swing_high_pct": 2.49,
        "swing_low": 233.589996,
        "swing_low_pct": -4.4,
        "volume_ratio": 1.1,
        "volume_expanding": false,
        "volume_today": 5976442,
        "volume_avg": 5410535
      },
      "analysis": "AMZN (NASDAQ) long scalp \u2014 squeeze released. momentum \u25b2 +1.4854. Support $243.3300. Stop $240.9094 (1.4% risk), target $251.2387 (2.0:1 R:R)."
    },
    {
      "symbol": "META",
      "name": "Meta Platforms",
      "sector": "Technology",
      "asset_type": "nasdaq",
      "dir": "SHORT",
      "grade": "B",
      "score": 5,
      "score_max": 10,
      "chips": [
        "MOMENTUM ALIGNED",
        "RESISTANCE @ 581.0100",
        "VOLUME EXPANSION"
      ],
      "weekly": false,
      "low_rr": false,
      "rr_text": "2.0:1",
      "target_2r": false,
      "liquidity": "LIQUID",
      "price": 577.2199707,
      "y_close": 577.2199707,
      "open": 577.2199707,
      "open_pct": 0.0,
      "current_pct": 0.0,
      "day_pct": 0.0,
      "entry": 577.2199707,
      "stop": 586.07551412,
      "target": 559.50888385,
      "rr": 2.0,
      "trail": 586.07551412,
      "stop_pct": 1.5,
      "p2_pct": 3.1,
      "target_basis": "atr",
      "spark": [
        566.61999512,
        566.70001221,
        590.34002686,
        596.75,
        598.89501953,
        594.71002197,
        595.53497314,
        591.25,
        593.48999023,
        593.5401001,
        596.88500977,
        596.33001709,
        596.16998291,
        598.2199707,
        598.80010986,
        600.29998779,
        585.04998779,
        580.54998779,
        580.29998779,
        579.44500732,
        575.84509277,
        569.83001709,
        567.48498535,
        569.90008545,
        572.98999023,
        576.0300293,
        577.90002441,
        573.5300293,
        574.68499756,
        577.2199707
      ],
      "trend": "blue",
      "turnover": 0,
      "detail": {
        "setup_type": "scalp",
        "entry": 577.219971,
        "stop": 586.075514,
        "target": 559.508884,
        "stop_pct": 1.53,
        "target_pct": 3.07,
        "notional": 5000,
        "units": 8,
        "risk_dollars": 70.84,
        "reward_dollars": 141.69,
        "brokerage_rt": 40,
        "net_loss": 110.84,
        "net_profit": 101.69,
        "eff_rr": 0.92,
        "sq_state": "RELEASED",
        "mom_val": -9.17992,
        "nearest_support": 576.070007,
        "support_pct": -0.2,
        "nearest_resistance": 581.01001,
        "resistance_pct": 0.66,
        "bb_upper": 604.05631,
        "bb_mid": 582.373264,
        "bb_lower": 560.690218,
        "kc_upper": 591.44503,
        "kc_lower": 573.301497,
        "atr": 5.90369562,
        "swing_high": 605.780029,
        "swing_high_pct": 4.95,
        "swing_low": 557.01001,
        "swing_low_pct": -3.5,
        "volume_ratio": 6.45,
        "volume_expanding": true,
        "volume_today": 12763390,
        "volume_avg": 1977939
      },
      "analysis": "META (NASDAQ) short scalp \u2014 squeeze released. momentum \u25bc -9.1799. Resistance $581.0100. Stop $586.0755 (1.5% risk), target $559.5089 (2.0:1 R:R)."
    },
    {
      "symbol": "NFLX",
      "name": "Netflix",
      "sector": "Communication",
      "asset_type": "nasdaq",
      "dir": "SHORT",
      "grade": "B",
      "score": 5,
      "score_max": 10,
      "chips": [
        "MOMENTUM ALIGNED",
        "RESISTANCE @ 79.2800",
        "VOLUME EXPANSION"
      ],
      "weekly": false,
      "low_rr": false,
      "rr_text": "2.0:1",
      "target_2r": false,
      "liquidity": "LIQUID",
      "price": 77.33000183,
      "y_close": 77.33000183,
      "open": 77.33000183,
      "open_pct": 0.0,
      "current_pct": 0.0,
      "day_pct": 0.0,
      "entry": 77.33000183,
      "stop": 78.41631367,
      "target": 75.15737814,
      "rr": 2.0,
      "trail": 78.41631367,
      "stop_pct": 1.4,
      "p2_pct": 2.8,
      "target_basis": "atr",
      "spark": [
        80.52500153,
        80.33499908,
        80.68499756,
        81.36000061,
        81.41000366,
        81.29000092,
        81.55000305,
        81.43000031,
        81.66999817,
        78.88500214,
        79.11499786,
        78.78500366,
        78.26999664,
        78.26629639,
        78.50499725,
        78.73999786,
        77.76999664,
        78.01000214,
        77.88500214,
        77.73999786,
        77.60500336,
        76.93499756,
        76.94999695,
        77.11000061,
        76.94999695,
        77.23880005,
        77.58000183,
        77.25,
        77.01499939,
        77.33000183
      ],
      "trend": "blue",
      "turnover": 0,
      "detail": {
        "setup_type": "scalp",
        "entry": 77.330002,
        "stop": 78.416314,
        "target": 75.157378,
        "stop_pct": 1.4,
        "target_pct": 2.81,
        "notional": 5000,
        "units": 64,
        "risk_dollars": 69.52,
        "reward_dollars": 139.05,
        "brokerage_rt": 40,
        "net_loss": 109.52,
        "net_profit": 99.05,
        "eff_rr": 0.9,
        "sq_state": "RELEASED",
        "mom_val": -1.016214,
        "nearest_support": 76.120003,
        "support_pct": -1.56,
        "nearest_resistance": 79.279999,
        "resistance_pct": 2.52,
        "bb_upper": 79.074581,
        "bb_mid": 77.752504,
        "bb_lower": 76.430427,
        "kc_upper": 78.842834,
        "kc_lower": 76.662175,
        "atr": 0.7242079,
        "swing_high": 82.894997,
        "swing_high_pct": 7.2,
        "swing_low": 76.120003,
        "swing_low_pct": -1.56,
        "volume_ratio": 1.81,
        "volume_expanding": true,
        "volume_today": 11797911,
        "volume_avg": 6505108
      },
      "analysis": "NFLX (NASDAQ) short scalp \u2014 squeeze released. momentum \u25bc -1.0162. Resistance $79.2800. Stop $78.4163 (1.4% risk), target $75.1574 (2.0:1 R:R)."
    },
    {
      "symbol": "CRM",
      "name": "Salesforce",
      "sector": "Technology",
      "asset_type": "nasdaq",
      "dir": "SHORT",
      "grade": "B",
      "score": 5,
      "score_max": 10,
      "chips": [
        "MOMENTUM ALIGNED",
        "RESISTANCE @ 157.0950",
        "VOLUME EXPANSION"
      ],
      "weekly": false,
      "low_rr": false,
      "rr_text": "2.0:1",
      "target_2r": false,
      "liquidity": "LIQUID",
      "price": 151.80999756,
      "y_close": 151.80999756,
      "open": 151.80999756,
      "open_pct": 0.0,
      "current_pct": 0.0,
      "day_pct": 0.0,
      "entry": 151.80999756,
      "stop": 154.76063124,
      "target": 145.9087302,
      "rr": 2.0,
      "trail": 154.76063124,
      "stop_pct": 1.9,
      "p2_pct": 3.9,
      "target_basis": "atr",
      "spark": [
        166.04499817,
        166.02999878,
        167.6401062,
        167.26499939,
        168.13000488,
        166.0,
        165.24000549,
        164.83000183,
        164.6499939,
        162.16000366,
        162.27000427,
        160.75999451,
        160.69999695,
        161.28999329,
        161.41999817,
        161.72000122,
        160.24000549,
        158.96000671,
        158.52000427,
        158.16000366,
        157.13000488,
        155.36500549,
        155.07000732,
        151.87460327,
        151.6499939,
        152.11999512,
        152.66999817,
        153.77000427,
        152.71499634,
        151.80999756
      ],
      "trend": "blue",
      "turnover": 0,
      "detail": {
        "setup_type": "scalp",
        "entry": 151.809998,
        "stop": 154.760631,
        "target": 145.90873,
        "stop_pct": 1.94,
        "target_pct": 3.89,
        "notional": 5000,
        "units": 32,
        "risk_dollars": 94.42,
        "reward_dollars": 188.84,
        "brokerage_rt": 40,
        "net_loss": 134.42,
        "net_profit": 148.84,
        "eff_rr": 1.11,
        "sq_state": "RELEASED",
        "mom_val": -5.584232,
        "nearest_support": 149.800003,
        "support_pct": -1.32,
        "nearest_resistance": 157.095001,
        "resistance_pct": 3.48,
        "bb_upper": 164.569139,
        "bb_mid": 156.910731,
        "bb_lower": 149.252323,
        "kc_upper": 159.885468,
        "kc_lower": 153.935993,
        "atr": 1.96708912,
        "swing_high": 183.839996,
        "swing_high_pct": 21.1,
        "swing_low": 149.800003,
        "swing_low_pct": -1.32,
        "volume_ratio": 3.0,
        "volume_expanding": true,
        "volume_today": 6164050,
        "volume_avg": 2053742
      },
      "analysis": "CRM (NASDAQ) short scalp \u2014 squeeze released. momentum \u25bc -5.5842. Resistance $157.0950. Stop $154.7606 (1.9% risk), target $145.9087 (2.0:1 R:R)."
    },
    {
      "symbol": "COST",
      "name": "Costco",
      "sector": "Consumer Staples",
      "asset_type": "nasdaq",
      "dir": "SHORT",
      "grade": "B",
      "score": 5,
      "score_max": 10,
      "chips": [
        "MOMENTUM ALIGNED",
        "RESISTANCE @ 964.3100",
        "VOLUME EXPANSION"
      ],
      "weekly": false,
      "low_rr": false,
      "rr_text": "2.0:1",
      "target_2r": false,
      "liquidity": "LIQUID",
      "price": 951.10998535,
      "y_close": 951.10998535,
      "open": 951.10998535,
      "open_pct": 0.0,
      "current_pct": 0.0,
      "day_pct": 0.0,
      "entry": 951.10998535,
      "stop": 959.72904207,
      "target": 933.8718719,
      "rr": 2.0,
      "trail": 959.72904207,
      "stop_pct": 0.9,
      "p2_pct": 1.8,
      "target_basis": "atr",
      "spark": [
        981.59002686,
        982.55999756,
        979.95001221,
        978.28497314,
        978.55999756,
        983.56500244,
        981.5,
        980.84997559,
        979.45001221,
        988.15002441,
        990.27502441,
        986.23797607,
        985.94000244,
        983.7388916,
        982.26501465,
        986.60998535,
        977.55792236,
        978.55999756,
        972.51000977,
        968.2199707,
        963.99499512,
        964.65997314,
        965.59997559,
        952.40997314,
        953.96258545,
        952.77502441,
        949.40002441,
        950.0,
        949.72998047,
        951.10998535
      ],
      "trend": "blue",
      "turnover": 0,
      "detail": {
        "setup_type": "scalp",
        "entry": 951.109985,
        "stop": 959.729042,
        "target": 933.871872,
        "stop_pct": 0.91,
        "target_pct": 1.81,
        "notional": 5000,
        "units": 5,
        "risk_dollars": 43.1,
        "reward_dollars": 86.19,
        "brokerage_rt": 40,
        "net_loss": 83.1,
        "net_profit": 46.19,
        "eff_rr": 0.56,
        "sq_state": "RELEASED",
        "mom_val": -23.272661,
        "nearest_support": 948.310974,
        "support_pct": -0.29,
        "nearest_resistance": 964.309998,
        "resistance_pct": 1.39,
        "bb_upper": 997.135343,
        "bb_mid": 968.277866,
        "bb_lower": 939.420388,
        "kc_upper": 977.267011,
        "kc_lower": 959.288721,
        "atr": 5.74603782,
        "swing_high": 995.380005,
        "swing_high_pct": 4.65,
        "swing_low": 948.310974,
        "swing_low_pct": -0.29,
        "volume_ratio": 1.47,
        "volume_expanding": true,
        "volume_today": 298821,
        "volume_avg": 203462
      },
      "analysis": "COST (NASDAQ) short scalp \u2014 squeeze released. momentum \u25bc -23.2727. Resistance $964.3100. Stop $959.7290 (0.9% risk), target $933.8719 (2.0:1 R:R)."
    },
    {
      "symbol": "MU",
      "name": "Micron Technology",
      "sector": "Technology",
      "asset_type": "nasdaq",
      "dir": "LONG",
      "grade": "B",
      "score": 5,
      "score_max": 10,
      "chips": [
        "MOMENTUM ALIGNED",
        "MOMENTUM ACCELERATING",
        "SUPPORT @ 1110.3999"
      ],
      "weekly": false,
      "low_rr": false,
      "rr_text": "2.0:1",
      "target_2r": false,
      "liquidity": "LIQUID",
      "price": 1131.91003418,
      "y_close": 1131.91003418,
      "open": 1131.91003418,
      "open_pct": 0.0,
      "current_pct": 0.0,
      "day_pct": 0.0,
      "entry": 1131.91003418,
      "stop": 1092.80603097,
      "target": 1210.1180406,
      "rr": 2.0,
      "trail": 1092.80603097,
      "stop_pct": 3.5,
      "p2_pct": 6.9,
      "target_basis": "atr",
      "spark": [
        989.51000977,
        980.71002197,
        1069.47998047,
        1074.32495117,
        1077.72998047,
        1078.56494141,
        1080.85925293,
        1086.22998047,
        1087.63000488,
        1071.04003906,
        1045.51000977,
        1054.25,
        1044.54504395,
        1043.93005371,
        1040.2800293,
        1020.45001221,
        1038.73498535,
        1046.02526855,
        1057.50012207,
        1066.42504883,
        1055.88500977,
        1081.28503418,
        1041.56005859,
        1115.56005859,
        1126.11999512,
        1124.16003418,
        1134.22509766,
        1144.97998047,
        1142.21496582,
        1131.91003418
      ],
      "trend": "blue",
      "turnover": 0,
      "detail": {
        "setup_type": "scalp",
        "entry": 1131.910034,
        "stop": 1092.806031,
        "target": 1210.118041,
        "stop_pct": 3.45,
        "target_pct": 6.91,
        "notional": 5000,
        "units": 4,
        "risk_dollars": 156.42,
        "reward_dollars": 312.83,
        "brokerage_rt": 40,
        "net_loss": 196.42,
        "net_profit": 272.83,
        "eff_rr": 1.39,
        "sq_state": "RELEASED",
        "mom_val": 71.038426,
        "nearest_support": 1110.399902,
        "support_pct": -1.9,
        "nearest_resistance": null,
        "resistance_pct": null,
        "bb_upper": 1160.37781,
        "bb_mid": 1077.777542,
        "bb_lower": 995.177274,
        "kc_upper": 1117.648683,
        "kc_lower": 1037.906401,
        "atr": 26.06933547,
        "swing_high": 1149.430054,
        "swing_high_pct": 1.55,
        "swing_low": 854.349976,
        "swing_low_pct": -24.52,
        "volume_ratio": 0.92,
        "volume_expanding": false,
        "volume_today": 5612882,
        "volume_avg": 6101308
      },
      "analysis": "MU (NASDAQ) long scalp \u2014 squeeze released. momentum \u25b2 +71.0384. Support $1110.3999. Stop $1092.8060 (3.5% risk), target $1210.1180 (2.0:1 R:R)."
    },
    {
      "symbol": "SPY",
      "name": "S&P 500 ETF",
      "sector": "Index",
      "asset_type": "nasdaq",
      "dir": "SHORT",
      "grade": "B",
      "score": 5,
      "score_max": 10,
      "chips": [
        "MOMENTUM ALIGNED",
        "RESISTANCE @ 746.9000",
        "VOLUME EXPANSION"
      ],
      "weekly": false,
      "low_rr": false,
      "rr_text": "2.0:1",
      "target_2r": false,
      "liquidity": "LIQUID",
      "price": 746.59002686,
      "y_close": 746.59002686,
      "open": 746.59002686,
      "open_pct": 0.0,
      "current_pct": 0.0,
      "day_pct": 0.0,
      "entry": 746.59002686,
      "stop": 751.38915373,
      "target": 736.99177313,
      "rr": 2.0,
      "trail": 751.38915373,
      "stop_pct": 0.6,
      "p2_pct": 1.3,
      "target_basis": "atr",
      "spark": [
        741.41998291,
        741.65997314,
        753.65002441,
        755.14001465,
        756.5,
        756.13000488,
        754.7199707,
        754.36999512,
        754.65997314,
        753.05999756,
        752.64990234,
        753.35998535,
        752.19000244,
        752.13500977,
        751.2199707,
        750.34997559,
        751.69000244,
        750.0,
        750.76000977,
        749.65997314,
        746.22497559,
        742.05999756,
        740.92999268,
        745.36999512,
        745.38000488,
        746.65002441,
        747.54998779,
        746.5,
        746.01000977,
        746.59002686
      ],
      "trend": "blue",
      "turnover": 0,
      "detail": {
        "setup_type": "scalp",
        "entry": 746.590027,
        "stop": 751.389154,
        "target": 736.991773,
        "stop_pct": 0.64,
        "target_pct": 1.29,
        "notional": 5000,
        "units": 6,
        "risk_dollars": 28.79,
        "reward_dollars": 57.59,
        "brokerage_rt": 40,
        "net_loss": 68.79,
        "net_profit": 17.59,
        "eff_rr": 0.26,
        "sq_state": "RELEASED",
        "mom_val": -2.251466,
        "nearest_support": 744.440002,
        "support_pct": -0.29,
        "nearest_resistance": 746.900024,
        "resistance_pct": 0.04,
        "bb_upper": 755.272816,
        "bb_mid": 748.363992,
        "bb_lower": 741.455169,
        "kc_upper": 753.339555,
        "kc_lower": 743.388429,
        "atr": 3.19941791,
        "swing_high": 756.679993,
        "swing_high_pct": 1.35,
        "swing_low": 722.590027,
        "swing_low_pct": -3.21,
        "volume_ratio": 1.34,
        "volume_expanding": true,
        "volume_today": 11540450,
        "volume_avg": 8589972
      },
      "analysis": "SPY (NASDAQ) short scalp \u2014 squeeze released. momentum \u25bc -2.2515. Resistance $746.9000. Stop $751.3892 (0.6% risk), target $736.9918 (2.0:1 R:R)."
    },
    {
      "symbol": "QQQ",
      "name": "Nasdaq-100 ETF",
      "sector": "Index",
      "asset_type": "nasdaq",
      "dir": "LONG",
      "grade": "B",
      "score": 5,
      "score_max": 10,
      "chips": [
        "MOMENTUM ALIGNED",
        "MOMENTUM ACCELERATING",
        "SUPPORT @ 735.6780"
      ],
      "weekly": false,
      "low_rr": false,
      "rr_text": "2.0:1",
      "target_2r": false,
      "liquidity": "LIQUID",
      "price": 739.69000244,
      "y_close": 739.69000244,
      "open": 739.69000244,
      "open_pct": 0.0,
      "current_pct": 0.0,
      "day_pct": 0.0,
      "entry": 739.69000244,
      "stop": 732.29003087,
      "target": 754.48994557,
      "rr": 2.0,
      "trail": 732.29003087,
      "stop_pct": 1.0,
      "p2_pct": 2.0,
      "target_basis": "atr",
      "spark": [
        721.55999756,
        721.32000732,
        740.99200439,
        743.11999512,
        744.47497559,
        744.01000977,
        743.03997803,
        742.82000732,
        743.80999756,
        739.10998535,
        735.60998535,
        735.67498779,
        733.64990234,
        733.85998535,
        733.14001465,
        729.7800293,
        734.83001709,
        732.63500977,
        733.65002441,
        732.78009033,
        728.68951416,
        725.84997559,
        722.40002441,
        735.52001953,
        736.97991943,
        739.26000977,
        739.99951172,
        739.59002686,
        739.47998047,
        739.69000244
      ],
      "trend": "blue",
      "turnover": 0,
      "detail": {
        "setup_type": "scalp",
        "entry": 739.690002,
        "stop": 732.290031,
        "target": 754.489946,
        "stop_pct": 1.0,
        "target_pct": 2.0,
        "notional": 5000,
        "units": 6,
        "risk_dollars": 44.4,
        "reward_dollars": 88.8,
        "brokerage_rt": 40,
        "net_loss": 84.4,
        "net_profit": 48.8,
        "eff_rr": 0.58,
        "sq_state": "RELEASED",
        "mom_val": 7.586642,
        "nearest_support": 735.677979,
        "support_pct": -0.54,
        "nearest_resistance": 744.759888,
        "resistance_pct": 0.69,
        "bb_upper": 743.378091,
        "bb_mid": 734.153452,
        "bb_lower": 724.928812,
        "kc_upper": 741.884995,
        "kc_lower": 726.421908,
        "atr": 4.93331438,
        "swing_high": 744.759888,
        "swing_high_pct": 0.69,
        "swing_low": 686.369995,
        "swing_low_pct": -7.21,
        "volume_ratio": 1.25,
        "volume_expanding": false,
        "volume_today": 7609540,
        "volume_avg": 6074047
      },
      "analysis": "QQQ (NASDAQ) long scalp \u2014 squeeze released. momentum \u25b2 +7.5866. Support $735.6780. Stop $732.2900 (1.0% risk), target $754.4899 (2.0:1 R:R)."
    },
    {
      "symbol": "NAS100",
      "name": "Nasdaq 100",
      "sector": "Index",
      "asset_type": "index",
      "dir": "SHORT",
      "grade": "B",
      "score": 5,
      "score_max": 10,
      "chips": [
        "MOMENTUM ALIGNED",
        "MOMENTUM ACCELERATING",
        "RESISTANCE @ 30520.0000"
      ],
      "weekly": false,
      "low_rr": false,
      "rr_text": "2.0:1",
      "target_2r": false,
      "liquidity": "LIQUID",
      "price": 30506.5,
      "y_close": 30506.5,
      "open": 30506.5,
      "open_pct": 0.0,
      "current_pct": 0.0,
      "day_pct": 0.0,
      "entry": 30506.5,
      "stop": 30660.81772333,
      "target": 30197.86455334,
      "rr": 2.0,
      "trail": 30660.81772333,
      "stop_pct": 0.5,
      "p2_pct": 1.0,
      "target_basis": "atr",
      "spark": [
        30141.75,
        30236.5,
        30312.25,
        30368.25,
        30380.0,
        30400.25,
        30398.75,
        30342.0,
        30354.0,
        30419.5,
        30444.5,
        30396.25,
        30488.5,
        30434.75,
        30423.5,
        30514.75,
        30468.75,
        30623.5,
        30640.75,
        30684.75,
        30708.5,
        30690.75,
        30693.5,
        30726.5,
        30662.75,
        30692.5,
        30642.75,
        30594.5,
        30593.75,
        30506.5
      ],
      "trend": "blue",
      "turnover": 0,
      "detail": {
        "setup_type": "scalp",
        "entry": 30506.5,
        "stop": 30660.817723,
        "target": 30197.864553,
        "stop_pct": 0.51,
        "target_pct": 1.01,
        "notional": 5000,
        "units": 0,
        "risk_dollars": 0.0,
        "reward_dollars": 0.0,
        "brokerage_rt": 40,
        "net_loss": 40.0,
        "net_profit": -40.0,
        "eff_rr": -1.0,
        "sq_state": "RELEASED",
        "mom_val": -15.332452,
        "nearest_support": 30500.0,
        "support_pct": -0.02,
        "nearest_resistance": 30520.0,
        "resistance_pct": 0.04,
        "bb_upper": 30796.816136,
        "bb_mid": 30581.6,
        "bb_lower": 30366.383864,
        "kc_upper": 30743.296688,
        "kc_lower": 30419.903312,
        "atr": 102.87848222,
        "swing_high": 30889.0,
        "swing_high_pct": 1.25,
        "swing_low": 29923.0,
        "swing_low_pct": -1.91,
        "volume_ratio": 0.18,
        "volume_expanding": false,
        "volume_today": 4486,
        "volume_avg": 25337
      },
      "analysis": "NAS100 (INDEX) short scalp \u2014 squeeze released. momentum \u25bc -15.3325. Resistance $30520.0000. Stop $30660.8177 (0.5% risk), target $30197.8646 (2.0:1 R:R)."
    },
    {
      "symbol": "BNB",
      "name": "BNB",
      "sector": "Crypto",
      "asset_type": "crypto",
      "dir": "LONG",
      "grade": "B",
      "score": 5,
      "score_max": 10,
      "chips": [
        "MOMENTUM ALIGNED",
        "MOMENTUM ACCELERATING",
        "SUPPORT @ 582.4000"
      ],
      "weekly": false,
      "low_rr": false,
      "rr_text": "2.0:1",
      "target_2r": false,
      "liquidity": "LIQUID",
      "price": 585.55999756,
      "y_close": 585.55999756,
      "open": 585.55999756,
      "open_pct": 0.0,
      "current_pct": 0.0,
      "day_pct": 0.0,
      "entry": 585.55999756,
      "stop": 581.26075742,
      "target": 594.15847783,
      "rr": 2.0,
      "trail": 581.26075742,
      "stop_pct": 0.7,
      "p2_pct": 1.5,
      "target_basis": "atr",
      "spark": [
        577.57000732,
        572.09997559,
        575.28997803,
        574.0,
        574.33001709,
        573.5,
        570.90002441,
        572.55999756,
        572.78997803,
        575.0,
        577.10998535,
        577.03997803,
        578.09997559,
        577.0300293,
        579.57000732,
        578.77001953,
        579.35998535,
        581.20001221,
        579.66998291,
        580.25,
        581.0,
        580.59002686,
        580.84002686,
        579.83001709,
        580.14001465,
        580.53997803,
        582.39001465,
        586.72998047,
        587.04998779,
        585.55999756
      ],
      "trend": "blue",
      "turnover": 0,
      "detail": {
        "setup_type": "scalp",
        "entry": 585.559998,
        "stop": 581.260757,
        "target": 594.158478,
        "stop_pct": 0.73,
        "target_pct": 1.47,
        "notional": 5000,
        "units": 8,
        "risk_dollars": 34.39,
        "reward_dollars": 68.79,
        "brokerage_rt": 40,
        "net_loss": 74.39,
        "net_profit": 28.79,
        "eff_rr": 0.39,
        "sq_state": "RELEASED",
        "mom_val": 5.57148,
        "nearest_support": 582.400024,
        "support_pct": -0.54,
        "nearest_resistance": 586.880005,
        "resistance_pct": 0.23,
        "bb_upper": 586.279856,
        "bb_mid": 580.638501,
        "bb_lower": 574.997146,
        "kc_upper": 585.181235,
        "kc_lower": 576.095767,
        "atr": 2.86616009,
        "swing_high": 603.599976,
        "swing_high_pct": 3.08,
        "swing_low": 570.299988,
        "swing_low_pct": -2.61,
        "volume_ratio": 0.03,
        "volume_expanding": false,
        "volume_today": 79744,
        "volume_avg": 2819008
      },
      "analysis": "BNB (CRYPTO) long scalp \u2014 squeeze released. momentum \u25b2 +5.5715. Support $582.4000. Stop $581.2608 (0.7% risk), target $594.1585 (2.0:1 R:R)."
    },
    {
      "symbol": "ADA",
      "name": "Cardano",
      "sector": "Crypto",
      "asset_type": "crypto",
      "dir": "LONG",
      "grade": "B",
      "score": 5,
      "score_max": 10,
      "chips": [
        "SQUEEZE BUILDING",
        "MOMENTUM ALIGNED",
        "SUPPORT @ 0.1626"
      ],
      "weekly": false,
      "low_rr": false,
      "rr_text": "2.0:1",
      "target_2r": false,
      "liquidity": "LIQUID",
      "price": 0.1627,
      "y_close": 0.1627,
      "open": 0.1627,
      "open_pct": 0.0,
      "current_pct": 0.0,
      "day_pct": 0.0,
      "entry": 0.1627,
      "stop": 0.16067755,
      "target": 0.1667449,
      "rr": 2.0,
      "trail": 0.16067755,
      "stop_pct": 1.2,
      "p2_pct": 2.5,
      "target_basis": "atr",
      "spark": [
        0.1619,
        0.16,
        0.16069999,
        0.16069999,
        0.1594,
        0.1604,
        0.1596,
        0.16,
        0.15979999,
        0.16060001,
        0.1622,
        0.16159999,
        0.16159999,
        0.1604,
        0.16159999,
        0.1611,
        0.16069999,
        0.1618,
        0.16060001,
        0.16159999,
        0.162,
        0.1622,
        0.16230001,
        0.162,
        0.16230001,
        0.1629,
        0.16339999,
        0.1635,
        0.1628,
        0.1627
      ],
      "trend": "blue",
      "turnover": 0,
      "detail": {
        "setup_type": "scalp",
        "entry": 0.1627,
        "stop": 0.160678,
        "target": 0.166745,
        "stop_pct": 1.24,
        "target_pct": 2.49,
        "notional": 5000,
        "units": 30731,
        "risk_dollars": 62.15,
        "reward_dollars": 124.3,
        "brokerage_rt": 40,
        "net_loss": 102.15,
        "net_profit": 84.3,
        "eff_rr": 0.83,
        "sq_state": "BUILDING",
        "mom_val": 0.001484,
        "nearest_support": 0.1626,
        "support_pct": -0.06,
        "nearest_resistance": 0.1638,
        "resistance_pct": 0.68,
        "bb_upper": 0.163643,
        "bb_mid": 0.161965,
        "bb_lower": 0.160287,
        "kc_upper": 0.164136,
        "kc_lower": 0.159794,
        "atr": 0.0013483,
        "swing_high": 0.1687,
        "swing_high_pct": 3.69,
        "swing_low": 0.1586,
        "swing_low_pct": -2.52,
        "volume_ratio": 0.92,
        "volume_expanding": false,
        "volume_today": 264672,
        "volume_avg": 288912
      },
      "analysis": "ADA (CRYPTO) long scalp \u2014 squeeze building (coiling). momentum \u25b2 +0.0015. Support $0.1626. Stop $0.1607 (1.2% risk), target $0.1667 (2.0:1 R:R)."
    },
    {
      "symbol": "AVAX",
      "name": "Avalanche",
      "sector": "Crypto",
      "asset_type": "crypto",
      "dir": "LONG",
      "grade": "B",
      "score": 5,
      "score_max": 10,
      "chips": [
        "MOMENTUM ALIGNED",
        "MOMENTUM ACCELERATING",
        "SUPPORT @ 5.9700"
      ],
      "weekly": false,
      "low_rr": false,
      "rr_text": "2.0:1",
      "target_2r": false,
      "liquidity": "LIQUID",
      "price": 6.13000011,
      "y_close": 6.13000011,
      "open": 6.13000011,
      "open_pct": 0.0,
      "current_pct": 0.0,
      "day_pct": 0.0,
      "entry": 6.13000011,
      "stop": 5.96234497,
      "target": 6.4653104,
      "rr": 2.0,
      "trail": 5.96234497,
      "stop_pct": 2.7,
      "p2_pct": 5.5,
      "target_basis": "atr",
      "spark": [
        6.13999987,
        6.03999996,
        6.05999994,
        6.03999996,
        5.98000002,
        6.05000019,
        6.05999994,
        6.03999996,
        6.03999996,
        6.11000013,
        6.17000008,
        6.11000013,
        6.11000013,
        6.07999992,
        6.0,
        5.90999985,
        5.88000011,
        5.92999983,
        5.92999983,
        5.92999983,
        5.88999987,
        5.9000001,
        5.94000006,
        5.92999983,
        5.94999981,
        5.96999979,
        6.03000021,
        5.94000006,
        6.13999987,
        6.13000011
      ],
      "trend": "blue",
      "turnover": 0,
      "detail": {
        "setup_type": "scalp",
        "entry": 6.13,
        "stop": 5.962345,
        "target": 6.46531,
        "stop_pct": 2.73,
        "target_pct": 5.47,
        "notional": 5000,
        "units": 815,
        "risk_dollars": 136.64,
        "reward_dollars": 273.28,
        "brokerage_rt": 40,
        "net_loss": 176.64,
        "net_profit": 233.28,
        "eff_rr": 1.32,
        "sq_state": "RELEASED",
        "mom_val": 0.112808,
        "nearest_support": 5.97,
        "support_pct": -2.61,
        "nearest_resistance": 6.19,
        "resistance_pct": 0.98,
        "bb_upper": 6.178354,
        "bb_mid": 5.9935,
        "bb_lower": 5.808646,
        "kc_upper": 6.150109,
        "kc_lower": 5.836891,
        "atr": 0.1117701,
        "swing_high": 6.8,
        "swing_high_pct": 10.93,
        "swing_low": 5.68,
        "swing_low_pct": -7.34,
        "volume_ratio": 0.05,
        "volume_expanding": false,
        "volume_today": 559744,
        "volume_avg": 10567278
      },
      "analysis": "AVAX (CRYPTO) long scalp \u2014 squeeze released. momentum \u25b2 +0.1128. Support $5.9700. Stop $5.9623 (2.7% risk), target $6.4653 (2.0:1 R:R)."
    },
    {
      "symbol": "LINK",
      "name": "Chainlink",
      "sector": "Crypto",
      "asset_type": "crypto",
      "dir": "LONG",
      "grade": "B",
      "score": 5,
      "score_max": 10,
      "chips": [
        "SQUEEZE BUILDING",
        "MOMENTUM ALIGNED",
        "SUPPORT @ 7.8860"
      ],
      "weekly": false,
      "low_rr": false,
      "rr_text": "2.0:1",
      "target_2r": false,
      "liquidity": "LIQUID",
      "price": 7.93300009,
      "y_close": 7.93300009,
      "open": 7.93300009,
      "open_pct": 0.0,
      "current_pct": 0.0,
      "day_pct": 0.0,
      "entry": 7.93300009,
      "stop": 7.84585295,
      "target": 8.10729436,
      "rr": 2.0,
      "trail": 7.84585295,
      "stop_pct": 1.1,
      "p2_pct": 2.2,
      "target_basis": "atr",
      "spark": [
        7.87300014,
        7.81899977,
        7.88399982,
        7.88999987,
        7.83599997,
        7.84700012,
        7.829,
        7.82600021,
        7.80700016,
        7.85400009,
        7.92399979,
        7.89099979,
        7.89300013,
        7.85900021,
        7.90100002,
        7.8829999,
        7.87099981,
        7.91699982,
        7.88199997,
        7.91699982,
        7.94399977,
        7.87900019,
        7.90399981,
        7.86800003,
        7.88500023,
        7.92000008,
        7.98000002,
        7.98199987,
        7.954,
        7.93300009
      ],
      "trend": "blue",
      "turnover": 0,
      "detail": {
        "setup_type": "scalp",
        "entry": 7.933,
        "stop": 7.845853,
        "target": 8.107294,
        "stop_pct": 1.1,
        "target_pct": 2.2,
        "notional": 5000,
        "units": 630,
        "risk_dollars": 54.9,
        "reward_dollars": 109.81,
        "brokerage_rt": 40,
        "net_loss": 94.9,
        "net_profit": 69.81,
        "eff_rr": 0.74,
        "sq_state": "BUILDING",
        "mom_val": 0.05979,
        "nearest_support": 7.886,
        "support_pct": -0.59,
        "nearest_resistance": 7.944,
        "resistance_pct": 0.14,
        "bb_upper": 7.978404,
        "bb_mid": 7.90935,
        "bb_lower": 7.840296,
        "kc_upper": 8.003653,
        "kc_lower": 7.815047,
        "atr": 0.05809809,
        "swing_high": 8.13,
        "swing_high_pct": 2.48,
        "swing_low": 7.766,
        "swing_low_pct": -2.11,
        "volume_ratio": 0.09,
        "volume_expanding": false,
        "volume_today": 50096,
        "volume_avg": 532520
      },
      "analysis": "LINK (CRYPTO) long scalp \u2014 squeeze building (coiling). momentum \u25b2 +0.0598. Support $7.8860. Stop $7.8459 (1.1% risk), target $8.1073 (2.0:1 R:R)."
    },
    {
      "symbol": "LTC",
      "name": "Litecoin",
      "sector": "Crypto",
      "asset_type": "crypto",
      "dir": "LONG",
      "grade": "B",
      "score": 5,
      "score_max": 10,
      "chips": [
        "SQUEEZE BUILDING",
        "MOMENTUM ALIGNED",
        "SUPPORT @ 44.0000"
      ],
      "weekly": false,
      "low_rr": false,
      "rr_text": "2.0:1",
      "target_2r": false,
      "liquidity": "LIQUID",
      "price": 44.04999924,
      "y_close": 44.04999924,
      "open": 44.04999924,
      "open_pct": 0.0,
      "current_pct": 0.0,
      "day_pct": 0.0,
      "entry": 44.04999924,
      "stop": 43.66523297,
      "target": 44.81953179,
      "rr": 2.0,
      "trail": 43.66523297,
      "stop_pct": 0.9,
      "p2_pct": 1.7,
      "target_basis": "atr",
      "spark": [
        43.52999878,
        43.22999954,
        43.47000122,
        43.52000046,
        43.40999985,
        43.45000076,
        43.36999893,
        43.40999985,
        43.45000076,
        43.70999908,
        44.0,
        44.06000137,
        44.40999985,
        44.27999878,
        44.11999893,
        44.15999985,
        43.90000153,
        44.06000137,
        43.77000046,
        43.81000137,
        44.02999878,
        43.88999939,
        43.93000031,
        43.86000061,
        43.88999939,
        43.95999908,
        44.15999985,
        44.33000183,
        44.09000015,
        44.04999924
      ],
      "trend": "blue",
      "turnover": 0,
      "detail": {
        "setup_type": "scalp",
        "entry": 44.049999,
        "stop": 43.665233,
        "target": 44.819532,
        "stop_pct": 0.87,
        "target_pct": 1.75,
        "notional": 5000,
        "units": 113,
        "risk_dollars": 43.48,
        "reward_dollars": 86.96,
        "brokerage_rt": 40,
        "net_loss": 83.48,
        "net_profit": 46.96,
        "eff_rr": 0.56,
        "sq_state": "BUILDING",
        "mom_val": 0.152336,
        "nearest_support": 44.0,
        "support_pct": -0.11,
        "nearest_resistance": 44.060001,
        "resistance_pct": 0.02,
        "bb_upper": 44.3727,
        "bb_mid": 44.038,
        "bb_lower": 43.7033,
        "kc_upper": 44.447593,
        "kc_lower": 43.628407,
        "atr": 0.25651085,
        "swing_high": 45.029999,
        "swing_high_pct": 2.22,
        "swing_low": 42.950001,
        "swing_low_pct": -2.5,
        "volume_ratio": 1.24,
        "volume_expanding": false,
        "volume_today": 820496,
        "volume_avg": 661303
      },
      "analysis": "LTC (CRYPTO) long scalp \u2014 squeeze building (coiling). momentum \u25b2 +0.1523. Support $44.0000. Stop $43.6652 (0.9% risk), target $44.8195 (2.0:1 R:R)."
    },
    {
      "symbol": "MSFT",
      "name": "Microsoft",
      "sector": "Technology",
      "asset_type": "nasdaq",
      "dir": "SHORT",
      "grade": "B",
      "score": 4,
      "score_max": 10,
      "chips": [
        "MOMENTUM ALIGNED",
        "RESISTANCE @ 381.3700"
      ],
      "weekly": false,
      "low_rr": false,
      "rr_text": "2.0:1",
      "target_2r": false,
      "liquidity": "LIQUID",
      "price": 379.04998779,
      "y_close": 379.04998779,
      "open": 379.04998779,
      "open_pct": 0.0,
      "current_pct": 0.0,
      "day_pct": 0.0,
      "entry": 379.04998779,
      "stop": 383.95626446,
      "target": 369.23743444,
      "rr": 2.0,
      "trail": 383.95626446,
      "stop_pct": 1.3,
      "p2_pct": 2.6,
      "target_basis": "atr",
      "spark": [
        389.42001343,
        390.67001343,
        398.32998657,
        398.48999023,
        401.57501221,
        399.48239136,
        398.9750061,
        398.45010376,
        399.97000122,
        393.09500122,
        393.42001343,
        391.84500122,
        391.5,
        392.11999512,
        393.11999512,
        393.92001343,
        387.38000488,
        385.42001343,
        385.375,
        384.89001465,
        383.01998901,
        379.02999878,
        378.86999512,
        377.22000122,
        375.16500854,
        378.59500122,
        379.69500732,
        377.61801147,
        378.0296936,
        379.04998779
      ],
      "trend": "blue",
      "turnover": 0,
      "detail": {
        "setup_type": "scalp",
        "entry": 379.049988,
        "stop": 383.956264,
        "target": 369.237434,
        "stop_pct": 1.29,
        "target_pct": 2.59,
        "notional": 5000,
        "units": 13,
        "risk_dollars": 63.78,
        "reward_dollars": 127.56,
        "brokerage_rt": 40,
        "net_loss": 103.78,
        "net_profit": 87.56,
        "eff_rr": 0.84,
        "sq_state": "RELEASED",
        "mom_val": -7.776206,
        "nearest_support": 373.279999,
        "support_pct": -1.52,
        "nearest_resistance": 381.369995,
        "resistance_pct": 0.61,
        "bb_upper": 396.860978,
        "bb_mid": 384.264137,
        "bb_lower": 371.667297,
        "kc_upper": 389.249402,
        "kc_lower": 379.278872,
        "atr": 3.27085112,
        "swing_high": 413.25,
        "swing_high_pct": 9.02,
        "swing_low": 373.279999,
        "swing_low_pct": -1.52,
        "volume_ratio": 0.96,
        "volume_expanding": false,
        "volume_today": 4475343,
        "volume_avg": 4638037
      },
      "analysis": "MSFT (NASDAQ) short scalp \u2014 squeeze released. momentum \u25bc -7.7762. Resistance $381.3700. Stop $383.9563 (1.3% risk), target $369.2374 (2.0:1 R:R)."
    },
    {
      "symbol": "GOOGL",
      "name": "Alphabet",
      "sector": "Technology",
      "asset_type": "nasdaq",
      "dir": "LONG",
      "grade": "B",
      "score": 4,
      "score_max": 10,
      "chips": [
        "MOMENTUM ACCELERATING",
        "SUPPORT @ 367.0750",
        "VOLUME EXPANSION"
      ],
      "weekly": false,
      "low_rr": false,
      "rr_text": "2.0:1",
      "target_2r": false,
      "liquidity": "LIQUID",
      "price": 367.98999023,
      "y_close": 367.98999023,
      "open": 367.98999023,
      "open_pct": 0.0,
      "current_pct": 0.0,
      "day_pct": 0.0,
      "entry": 367.98999023,
      "stop": 362.80085205,
      "target": 378.3682666,
      "rr": 2.0,
      "trail": 362.80085205,
      "stop_pct": 1.4,
      "p2_pct": 2.8,
      "target_basis": "atr",
      "spark": [
        360.5,
        359.67001343,
        369.10501099,
        372.36999512,
        371.03500366,
        371.67001343,
        371.45010376,
        369.83999634,
        369.30999756,
        370.44000244,
        375.2250061,
        372.20999146,
        370.42001343,
        372.33999634,
        372.37060547,
        373.27999878,
        366.82000732,
        364.11999512,
        365.73999023,
        365.15509033,
        365.65499878,
        362.51998901,
        363.69000244,
        361.85501099,
        364.00149536,
        366.33999634,
        367.84500122,
        367.69000244,
        367.61999512,
        367.98999023
      ],
      "trend": "blue",
      "turnover": 0,
      "detail": {
        "setup_type": "scalp",
        "entry": 367.98999,
        "stop": 362.800852,
        "target": 378.368267,
        "stop_pct": 1.41,
        "target_pct": 2.82,
        "notional": 5000,
        "units": 13,
        "risk_dollars": 67.46,
        "reward_dollars": 134.92,
        "brokerage_rt": 40,
        "net_loss": 107.46,
        "net_profit": 94.92,
        "eff_rr": 0.88,
        "sq_state": "RELEASED",
        "mom_val": -0.074642,
        "nearest_support": 367.075012,
        "support_pct": -0.25,
        "nearest_resistance": 368.554993,
        "resistance_pct": 0.15,
        "bb_upper": 375.1222,
        "bb_mid": 367.644359,
        "bb_lower": 360.166518,
        "kc_upper": 373.041241,
        "kc_lower": 362.247477,
        "atr": 3.45942546,
        "swing_high": 375.850006,
        "swing_high_pct": 2.14,
        "swing_low": 346.359985,
        "swing_low_pct": -5.88,
        "volume_ratio": 1.57,
        "volume_expanding": true,
        "volume_today": 4604925,
        "volume_avg": 2929372
      },
      "analysis": "GOOGL (NASDAQ) long scalp \u2014 squeeze released. momentum \u25b2 -0.0746. Support $367.0750. Stop $362.8009 (1.4% risk), target $378.3683 (2.0:1 R:R)."
    },
    {
      "symbol": "PLTR",
      "name": "Palantir",
      "sector": "Technology",
      "asset_type": "nasdaq",
      "dir": "SHORT",
      "grade": "B",
      "score": 4,
      "score_max": 10,
      "chips": [
        "MOMENTUM ALIGNED",
        "RESISTANCE @ 128.8000"
      ],
      "weekly": false,
      "low_rr": false,
      "rr_text": "2.0:1",
      "target_2r": false,
      "liquidity": "LIQUID",
      "price": 128.49000549,
      "y_close": 128.49000549,
      "open": 128.49000549,
      "open_pct": 0.0,
      "current_pct": 0.0,
      "day_pct": 0.0,
      "entry": 128.49000549,
      "stop": 131.35699472,
      "target": 122.75602703,
      "rr": 2.0,
      "trail": 131.35699472,
      "stop_pct": 2.2,
      "p2_pct": 4.5,
      "target_basis": "atr",
      "spark": [
        128.19500732,
        127.98000336,
        132.46000671,
        133.9750061,
        134.77999878,
        133.875,
        134.13000488,
        134.25999451,
        134.69999695,
        130.44999695,
        131.08999634,
        130.79319763,
        130.94000244,
        131.12460327,
        132.32000732,
        133.24000549,
        134.32499695,
        134.84500122,
        135.34500122,
        134.79499817,
        133.94000244,
        131.52999878,
        130.66000366,
        126.93000031,
        126.45500183,
        128.36999512,
        128.69000244,
        127.91840363,
        128.42999268,
        128.49000549
      ],
      "trend": "blue",
      "turnover": 0,
      "detail": {
        "setup_type": "scalp",
        "entry": 128.490005,
        "stop": 131.356995,
        "target": 122.756027,
        "stop_pct": 2.23,
        "target_pct": 4.46,
        "notional": 5000,
        "units": 38,
        "risk_dollars": 108.95,
        "reward_dollars": 217.89,
        "brokerage_rt": 40,
        "net_loss": 148.95,
        "net_profit": 177.89,
        "eff_rr": 1.19,
        "sq_state": "RELEASED",
        "mom_val": -4.383,
        "nearest_support": 127.349998,
        "support_pct": -0.89,
        "nearest_resistance": 128.800003,
        "resistance_pct": 0.24,
        "bb_upper": 136.431235,
        "bb_mid": 131.011561,
        "bb_lower": 125.591887,
        "kc_upper": 133.87917,
        "kc_lower": 128.143951,
        "atr": 1.91132615,
        "swing_high": 136.990005,
        "swing_high_pct": 6.62,
        "swing_low": 125.010002,
        "swing_low_pct": -2.71,
        "volume_ratio": 1.01,
        "volume_expanding": false,
        "volume_today": 4406407,
        "volume_avg": 4371817
      },
      "analysis": "PLTR (NASDAQ) short scalp \u2014 squeeze released. momentum \u25bc -4.3830. Resistance $128.8000. Stop $131.3570 (2.2% risk), target $122.7560 (2.0:1 R:R)."
    },
    {
      "symbol": "ADBE",
      "name": "Adobe",
      "sector": "Technology",
      "asset_type": "nasdaq",
      "dir": "SHORT",
      "grade": "B",
      "score": 4,
      "score_max": 10,
      "chips": [
        "MOMENTUM ALIGNED",
        "RESISTANCE @ 196.9000"
      ],
      "weekly": false,
      "low_rr": false,
      "rr_text": "2.0:1",
      "target_2r": false,
      "liquidity": "LIQUID",
      "price": 195.16000366,
      "y_close": 195.16000366,
      "open": 195.16000366,
      "open_pct": 0.0,
      "current_pct": 0.0,
      "day_pct": 0.0,
      "entry": 195.16000366,
      "stop": 199.20227023,
      "target": 187.07547051,
      "rr": 2.0,
      "trail": 199.20227023,
      "stop_pct": 2.1,
      "p2_pct": 4.1,
      "target_basis": "atr",
      "spark": [
        204.88200378,
        204.01499939,
        208.69999695,
        208.96000671,
        210.17500305,
        207.97990417,
        207.52000427,
        205.83999634,
        206.27000427,
        207.58999634,
        209.52999878,
        208.16000366,
        206.80999756,
        206.86500549,
        206.92999268,
        207.36000061,
        203.32000732,
        202.03999329,
        203.22000122,
        202.44009399,
        201.22000122,
        197.77999878,
        196.27000427,
        194.10499573,
        193.66000366,
        193.88499451,
        194.625,
        196.19500732,
        195.31500244,
        195.16000366
      ],
      "trend": "blue",
      "turnover": 0,
      "detail": {
        "setup_type": "scalp",
        "entry": 195.160004,
        "stop": 199.20227,
        "target": 187.075471,
        "stop_pct": 2.07,
        "target_pct": 4.14,
        "notional": 5000,
        "units": 25,
        "risk_dollars": 101.06,
        "reward_dollars": 202.11,
        "brokerage_rt": 40,
        "net_loss": 141.06,
        "net_profit": 162.11,
        "eff_rr": 1.15,
        "sq_state": "RELEASED",
        "mom_val": -7.026065,
        "nearest_support": 190.119995,
        "support_pct": -2.58,
        "nearest_resistance": 196.899994,
        "resistance_pct": 0.89,
        "bb_upper": 211.652658,
        "bb_mid": 200.744505,
        "bb_lower": 189.836352,
        "kc_upper": 205.015407,
        "kc_lower": 196.473604,
        "atr": 2.69484438,
        "swing_high": 247.389999,
        "swing_high_pct": 26.76,
        "swing_low": 190.119995,
        "swing_low_pct": -2.58,
        "volume_ratio": 0.93,
        "volume_expanding": false,
        "volume_today": 1091594,
        "volume_avg": 1176061
      },
      "analysis": "ADBE (NASDAQ) short scalp \u2014 squeeze released. momentum \u25bc -7.0261. Resistance $196.9000. Stop $199.2023 (2.1% risk), target $187.0755 (2.0:1 R:R)."
    },
    {
      "symbol": "GLD",
      "name": "Gold ETF",
      "sector": "Commodities",
      "asset_type": "nasdaq",
      "dir": "SHORT",
      "grade": "B",
      "score": 4,
      "score_max": 10,
      "chips": [
        "MOMENTUM ALIGNED",
        "RESISTANCE @ 388.7500"
      ],
      "weekly": false,
      "low_rr": false,
      "rr_text": "2.0:1",
      "target_2r": false,
      "liquidity": "LIQUID",
      "price": 387.08499146,
      "y_close": 387.08499146,
      "open": 387.08499146,
      "open_pct": 0.0,
      "current_pct": 0.0,
      "day_pct": 0.0,
      "entry": 387.08499146,
      "stop": 390.9858457,
      "target": 379.28328299,
      "rr": 2.0,
      "trail": 390.9858457,
      "stop_pct": 1.0,
      "p2_pct": 2.0,
      "target_basis": "atr",
      "spark": [
        386.32000732,
        386.54998779,
        400.45001221,
        399.6000061,
        398.57000732,
        397.33999634,
        396.8999939,
        396.58999634,
        396.54000854,
        396.41000366,
        397.02999878,
        398.75500488,
        397.84991455,
        398.47000122,
        398.29000854,
        397.73001099,
        400.02999878,
        399.54998779,
        400.5,
        400.10998535,
        393.80999756,
        387.88000488,
        388.69000244,
        389.57501221,
        388.76000977,
        387.73999023,
        387.85998535,
        387.89001465,
        385.91000366,
        387.08499146
      ],
      "trend": "blue",
      "turnover": 0,
      "detail": {
        "setup_type": "scalp",
        "entry": 387.084991,
        "stop": 390.985846,
        "target": 379.283283,
        "stop_pct": 1.01,
        "target_pct": 2.02,
        "notional": 5000,
        "units": 12,
        "risk_dollars": 46.81,
        "reward_dollars": 93.62,
        "brokerage_rt": 40,
        "net_loss": 86.81,
        "net_profit": 53.62,
        "eff_rr": 0.62,
        "sq_state": "RELEASED",
        "mom_val": -9.933074,
        "nearest_support": 387.079987,
        "support_pct": -0.0,
        "nearest_resistance": 388.75,
        "resistance_pct": 0.43,
        "bb_upper": 404.480954,
        "bb_mid": 393.675746,
        "bb_lower": 382.870538,
        "kc_upper": 397.620413,
        "kc_lower": 389.731079,
        "atr": 2.60056949,
        "swing_high": 402.040009,
        "swing_high_pct": 3.86,
        "swing_low": 371.880005,
        "swing_low_pct": -3.93,
        "volume_ratio": 0.69,
        "volume_expanding": false,
        "volume_today": 846081,
        "volume_avg": 1224289
      },
      "analysis": "GLD (NASDAQ) short scalp \u2014 squeeze released. momentum \u25bc -9.9331. Resistance $388.7500. Stop $390.9858 (1.0% risk), target $379.2833 (2.0:1 R:R)."
    },
    {
      "symbol": "SLV",
      "name": "Silver ETF",
      "sector": "Commodities",
      "asset_type": "nasdaq",
      "dir": "SHORT",
      "grade": "B",
      "score": 4,
      "score_max": 10,
      "chips": [
        "MOMENTUM ALIGNED",
        "RESISTANCE @ 61.1450"
      ],
      "weekly": false,
      "low_rr": false,
      "rr_text": "2.0:1",
      "target_2r": false,
      "liquidity": "LIQUID",
      "price": 59.50999832,
      "y_close": 59.50999832,
      "open": 59.50999832,
      "open_pct": 0.0,
      "current_pct": 0.0,
      "day_pct": 0.0,
      "entry": 59.50999832,
      "stop": 60.65360989,
      "target": 57.22277519,
      "rr": 2.0,
      "trail": 60.65360989,
      "stop_pct": 1.9,
      "p2_pct": 3.8,
      "target_basis": "atr",
      "spark": [
        61.34000015,
        61.27999878,
        64.32499695,
        63.90000153,
        63.61999893,
        63.43500137,
        63.42499924,
        63.36500168,
        63.47000122,
        62.93500137,
        63.18000031,
        63.59009933,
        63.3045578,
        63.64500046,
        63.58499908,
        63.40000153,
        63.97569275,
        63.88999939,
        63.96500015,
        63.99499893,
        62.5298996,
        61.09999847,
        60.61999893,
        60.16999817,
        59.67499924,
        59.77000046,
        59.70000076,
        59.73500061,
        58.95500183,
        59.50999832
      ],
      "trend": "blue",
      "turnover": 0,
      "detail": {
        "setup_type": "scalp",
        "entry": 59.509998,
        "stop": 60.65361,
        "target": 57.222775,
        "stop_pct": 1.92,
        "target_pct": 3.84,
        "notional": 5000,
        "units": 84,
        "risk_dollars": 96.06,
        "reward_dollars": 192.13,
        "brokerage_rt": 40,
        "net_loss": 136.06,
        "net_profit": 152.13,
        "eff_rr": 1.12,
        "sq_state": "RELEASED",
        "mom_val": -3.486187,
        "nearest_support": 58.220001,
        "support_pct": -2.17,
        "nearest_resistance": 61.145,
        "resistance_pct": 2.75,
        "bb_upper": 65.672083,
        "bb_mid": 61.914762,
        "bb_lower": 58.157441,
        "kc_upper": 63.059254,
        "kc_lower": 60.77027,
        "atr": 0.76240771,
        "swing_high": 64.690002,
        "swing_high_pct": 8.7,
        "swing_low": 57.299999,
        "swing_low_pct": -3.71,
        "volume_ratio": 1.18,
        "volume_expanding": false,
        "volume_today": 4226114,
        "volume_avg": 3578560
      },
      "analysis": "SLV (NASDAQ) short scalp \u2014 squeeze released. momentum \u25bc -3.4862. Resistance $61.1450. Stop $60.6536 (1.9% risk), target $57.2228 (2.0:1 R:R)."
    },
    {
      "symbol": "SOL",
      "name": "Solana",
      "sector": "Crypto",
      "asset_type": "crypto",
      "dir": "LONG",
      "grade": "B",
      "score": 4,
      "score_max": 10,
      "chips": [
        "MOMENTUM ALIGNED",
        "SUPPORT @ 70.5700"
      ],
      "weekly": false,
      "low_rr": false,
      "rr_text": "2.0:1",
      "target_2r": false,
      "liquidity": "LIQUID",
      "price": 71.44999695,
      "y_close": 71.44999695,
      "open": 71.44999695,
      "open_pct": 0.0,
      "current_pct": 0.0,
      "day_pct": 0.0,
      "entry": 71.44999695,
      "stop": 70.4569364,
      "target": 73.43611804,
      "rr": 2.0,
      "trail": 70.4569364,
      "stop_pct": 1.4,
      "p2_pct": 2.8,
      "target_basis": "atr",
      "spark": [
        68.98000336,
        68.25,
        68.63999939,
        68.69000244,
        68.30999756,
        68.58999634,
        68.23999786,
        68.25,
        68.19000244,
        68.55000305,
        69.22000122,
        69.08000183,
        69.26000214,
        68.65000153,
        69.26000214,
        68.98999786,
        68.88999939,
        69.19000244,
        68.94000244,
        69.34999847,
        69.68000031,
        69.56999969,
        69.75,
        69.56999969,
        69.93000031,
        70.77999878,
        71.73000336,
        72.05999756,
        71.51999664,
        71.44999695
      ],
      "trend": "blue",
      "turnover": 0,
      "detail": {
        "setup_type": "scalp",
        "entry": 71.449997,
        "stop": 70.456936,
        "target": 73.436118,
        "stop_pct": 1.39,
        "target_pct": 2.78,
        "notional": 5000,
        "units": 69,
        "risk_dollars": 68.52,
        "reward_dollars": 137.04,
        "brokerage_rt": 40,
        "net_loss": 108.52,
        "net_profit": 97.04,
        "eff_rr": 0.89,
        "sq_state": "RELEASED",
        "mom_val": 1.900049,
        "nearest_support": 70.57,
        "support_pct": -1.23,
        "nearest_resistance": 72.089996,
        "resistance_pct": 0.9,
        "bb_upper": 71.899439,
        "bb_mid": 69.8435,
        "bb_lower": 67.787561,
        "kc_upper": 70.849587,
        "kc_lower": 68.837413,
        "atr": 0.66204036,
        "swing_high": 72.589996,
        "swing_high_pct": 1.6,
        "swing_low": 67.870003,
        "swing_low_pct": -5.01,
        "volume_ratio": 0.83,
        "volume_expanding": false,
        "volume_today": 7474688,
        "volume_avg": 9033555
      },
      "analysis": "SOL (CRYPTO) long scalp \u2014 squeeze released. momentum \u25b2 +1.9000. Support $70.5700. Stop $70.4569 (1.4% risk), target $73.4361 (2.0:1 R:R)."
    },
    {
      "symbol": "TSLA",
      "name": "Tesla",
      "sector": "Consumer Disc",
      "asset_type": "nasdaq",
      "dir": "LONG",
      "grade": "C",
      "score": 3,
      "score_max": 10,
      "chips": [
        "MOMENTUM ACCELERATING",
        "SUPPORT @ 397.6800"
      ],
      "weekly": false,
      "low_rr": false,
      "rr_text": "2.0:1",
      "target_2r": false,
      "liquidity": "LIQUID",
      "price": 400.42999268,
      "y_close": 400.42999268,
      "open": 400.42999268,
      "open_pct": 0.0,
      "current_pct": 0.0,
      "day_pct": 0.0,
      "entry": 400.42999268,
      "stop": 392.11477173,
      "target": 417.06043457,
      "rr": 2.0,
      "trail": 392.11477173,
      "stop_pct": 2.1,
      "p2_pct": 4.2,
      "target_basis": "atr",
      "spark": [
        403.1000061,
        406.44500732,
        411.37991333,
        409.80999756,
        411.38000488,
        409.44000244,
        410.02999878,
        409.67001343,
        411.22000122,
        403.0,
        405.19000244,
        405.23999023,
        404.6499939,
        405.6000061,
        407.04998779,
        404.67001343,
        401.67999268,
        398.67498779,
        404.63000488,
        404.23999023,
        401.23010254,
        397.7756958,
        396.32000732,
        386.13500977,
        389.54888916,
        392.20001221,
        395.19000244,
        394.19500732,
        395.86999512,
        400.42999268
      ],
      "trend": "blue",
      "turnover": 0,
      "detail": {
        "setup_type": "scalp",
        "entry": 400.429993,
        "stop": 392.114772,
        "target": 417.060435,
        "stop_pct": 2.08,
        "target_pct": 4.15,
        "notional": 5000,
        "units": 12,
        "risk_dollars": 99.78,
        "reward_dollars": 199.57,
        "brokerage_rt": 40,
        "net_loss": 139.78,
        "net_profit": 159.57,
        "eff_rr": 1.14,
        "sq_state": "RELEASED",
        "mom_val": -4.994537,
        "nearest_support": 397.679993,
        "support_pct": -0.69,
        "nearest_resistance": 400.540009,
        "resistance_pct": 0.03,
        "bb_upper": 411.142942,
        "bb_mid": 399.525984,
        "bb_lower": 387.909027,
        "kc_upper": 407.926169,
        "kc_lower": 391.1258,
        "atr": 5.54348063,
        "swing_high": 418.5,
        "swing_high_pct": 4.51,
        "swing_low": 380.149994,
        "swing_low_pct": -5.06,
        "volume_ratio": 1.21,
        "volume_expanding": false,
        "volume_today": 7043465,
        "volume_avg": 5809356
      },
      "analysis": "TSLA (NASDAQ) long scalp \u2014 squeeze released. momentum \u25b2 -4.9945. Support $397.6800. Stop $392.1148 (2.1% risk), target $417.0604 (2.0:1 R:R)."
    }
  ]
}