{
  "market": "scalp",
  "label": "SCALP",
  "setup_type": "scalp",
  "currency": "USD",
  "currency_symbol": "$",
  "timezone": "UTC",
  "tz_label": "UTC",
  "generated_at": "2026-06-23T11:48:32+00:00",
  "timeframe": "1h",
  "scanned": 34,
  "quality_skipped": 20,
  "universe_size": 64,
  "score_max": 10,
  "brokerage": 20,
  "position_size": 1000,
  "leverage": 5,
  "risk_per_trade": 100,
  "max_daily_trades": 5,
  "trace_id": "b7718ce8",
  "scanner_version": "7.0.0",
  "scan_elapsed_s": 4.19,
  "pulse": [],
  "results": [
    {
      "symbol": "BNB",
      "name": "BNB",
      "sector": "Crypto",
      "asset_type": "crypto",
      "dir": "SHORT",
      "grade": "B",
      "score": 6,
      "score_max": 10,
      "chips": [
        "MOMENTUM ALIGNED",
        "MOMENTUM ACCELERATING",
        "RESISTANCE @ 582.9000",
        "VOLUME EXPANSION"
      ],
      "weekly": false,
      "low_rr": false,
      "rr_text": "2.0:1",
      "target_2r": false,
      "liquidity": "LIQUID",
      "price": 573.25,
      "y_close": 573.25,
      "open": 573.25,
      "open_pct": 0.0,
      "current_pct": 0.0,
      "day_pct": 0.0,
      "entry": 573.25,
      "stop": 578.86800528,
      "target": 562.01398943,
      "rr": 2.0,
      "atr": 3.74533686,
      "adx": 34.1,
      "market_regime": "trending",
      "trail": 578.86800528,
      "stop_pct": 1.0,
      "p2_pct": 2.0,
      "target_basis": "atr",
      "spark": [
        590.19000244,
        593.07000732,
        592.30999756,
        592.79998779,
        591.78997803,
        596.52001953,
        599.77001953,
        601.42999268,
        597.08001709,
        595.70001221,
        594.34002686,
        594.85998535,
        592.71002197,
        591.65997314,
        590.76000977,
        590.40997314,
        589.20001221,
        589.5300293,
        590.91998291,
        589.90997314,
        591.89001465,
        591.04998779,
        586.55999756,
        584.7199707,
        580.48999023,
        580.20001221,
        573.20001221,
        571.32000732,
        571.44000244,
        573.25
      ],
      "trend": "blue",
      "turnover": 0,
      "detail": {
        "setup_type": "scalp",
        "entry": 573.25,
        "stop": 578.868005,
        "target": 562.013989,
        "stop_pct": 0.98,
        "target_pct": 1.96,
        "notional": 5000,
        "units": 8,
        "risk_dollars": 44.94,
        "reward_dollars": 89.89,
        "brokerage_rt": 40,
        "net_loss": 84.94,
        "net_profit": 49.89,
        "eff_rr": 0.59,
        "sq_state": "RELEASED",
        "mom_val": -15.30105,
        "nearest_support": 570.059998,
        "support_pct": -0.56,
        "nearest_resistance": 582.900024,
        "resistance_pct": 1.68,
        "bb_upper": 601.473078,
        "bb_mid": 585.920999,
        "bb_lower": 570.36892,
        "kc_upper": 591.300388,
        "kc_lower": 580.54161,
        "atr": 3.74533686,
        "swing_high": 601.52002,
        "swing_high_pct": 4.93,
        "swing_low": 570.059998,
        "swing_low_pct": -0.56,
        "volume_ratio": 1.46,
        "volume_expanding": true,
        "volume_today": 14694912,
        "volume_avg": 10037081
      },
      "analysis": "BNB (CRYPTO) short scalp \u2014 squeeze released. momentum \u25bc -15.3011. Resistance $582.9000. Stop $578.8680 (1.0% risk), target $562.0140 (2.0:1 R:R)."
    },
    {
      "symbol": "AVAX",
      "name": "Avalanche",
      "sector": "Crypto",
      "asset_type": "crypto",
      "dir": "SHORT",
      "grade": "B",
      "score": 6,
      "score_max": 10,
      "chips": [
        "SQUEEZE BUILDING",
        "MOMENTUM ALIGNED",
        "RESISTANCE @ 6.2400",
        "VOLUME EXPANSION"
      ],
      "weekly": false,
      "low_rr": false,
      "rr_text": "2.0:1",
      "target_2r": false,
      "liquidity": "LIQUID",
      "price": 6.23999977,
      "y_close": 6.23999977,
      "open": 6.23999977,
      "open_pct": 0.0,
      "current_pct": 0.0,
      "day_pct": 0.0,
      "entry": 6.23999977,
      "stop": 6.35200387,
      "target": 6.01599157,
      "rr": 2.0,
      "atr": 0.0746694,
      "adx": 17.21,
      "market_regime": "ranging",
      "trail": 6.35200387,
      "stop_pct": 1.8,
      "p2_pct": 3.6,
      "target_basis": "atr",
      "spark": [
        6.25,
        6.28000021,
        6.26000023,
        6.23999977,
        6.26999998,
        6.36000013,
        6.4000001,
        6.46999979,
        6.32000017,
        6.30000019,
        6.30999994,
        6.30999994,
        6.26999998,
        6.26999998,
        6.26999998,
        6.23999977,
        6.19999981,
        6.23000002,
        6.26999998,
        6.26000023,
        6.30000019,
        6.30000019,
        6.26999998,
        6.23000002,
        6.17000008,
        6.1500001,
        6.11999989,
        6.19999981,
        6.19000006,
        6.23999977
      ],
      "trend": "blue",
      "turnover": 0,
      "detail": {
        "setup_type": "scalp",
        "entry": 6.24,
        "stop": 6.352004,
        "target": 6.015992,
        "stop_pct": 1.79,
        "target_pct": 3.59,
        "notional": 5000,
        "units": 801,
        "risk_dollars": 89.72,
        "reward_dollars": 179.43,
        "brokerage_rt": 40,
        "net_loss": 129.72,
        "net_profit": 139.43,
        "eff_rr": 1.07,
        "sq_state": "BUILDING",
        "mom_val": -0.05335,
        "nearest_support": 6.2,
        "support_pct": -0.64,
        "nearest_resistance": 6.24,
        "resistance_pct": 0.0,
        "bb_upper": 6.345071,
        "bb_mid": 6.24,
        "bb_lower": 6.134929,
        "kc_upper": 6.349824,
        "kc_lower": 6.130176,
        "atr": 0.0746694,
        "swing_high": 6.47,
        "swing_high_pct": 3.69,
        "swing_low": 6.01,
        "swing_low_pct": -3.69,
        "volume_ratio": 1.35,
        "volume_expanding": true,
        "volume_today": 3145408,
        "volume_avg": 2330365
      },
      "analysis": "AVAX (CRYPTO) short scalp \u2014 squeeze building (coiling). momentum \u25bc -0.0534. Resistance $6.2400. Stop $6.3520 (1.8% risk), target $6.0160 (2.0:1 R:R)."
    },
    {
      "symbol": "ETH",
      "name": "Ethereum",
      "sector": "Crypto",
      "asset_type": "crypto",
      "dir": "SHORT",
      "grade": "B",
      "score": 5,
      "score_max": 10,
      "chips": [
        "MOMENTUM ALIGNED",
        "RESISTANCE @ 1701.5800",
        "VOLUME EXPANSION"
      ],
      "weekly": false,
      "low_rr": false,
      "rr_text": "2.0:1",
      "target_2r": false,
      "liquidity": "LIQUID",
      "price": 1658.93994141,
      "y_close": 1658.93994141,
      "open": 1658.93994141,
      "open_pct": 0.0,
      "current_pct": 0.0,
      "day_pct": 0.0,
      "entry": 1658.93994141,
      "stop": 1680.63482113,
      "target": 1615.55018197,
      "rr": 2.0,
      "atr": 14.46325315,
      "adx": 29.03,
      "market_regime": "trending",
      "trail": 1680.63482113,
      "stop_pct": 1.3,
      "p2_pct": 2.6,
      "target_basis": "atr",
      "spark": [
        1732.85998535,
        1744.39001465,
        1746.01000977,
        1744.35998535,
        1747.0,
        1765.80004883,
        1762.0,
        1775.42004395,
        1752.4699707,
        1742.48999023,
        1737.97998047,
        1739.0,
        1731.14001465,
        1732.85998535,
        1732.65002441,
        1731.04003906,
        1722.39001465,
        1726.15002441,
        1729.30004883,
        1728.55004883,
        1730.47998047,
        1727.7800293,
        1717.14001465,
        1711.44995117,
        1690.09997559,
        1680.67004395,
        1646.4699707,
        1648.93994141,
        1650.55004883,
        1658.93994141
      ],
      "trend": "blue",
      "turnover": 0,
      "detail": {
        "setup_type": "scalp",
        "entry": 1658.939941,
        "stop": 1680.634821,
        "target": 1615.550182,
        "stop_pct": 1.31,
        "target_pct": 2.62,
        "notional": 5000,
        "units": 3,
        "risk_dollars": 65.08,
        "reward_dollars": 130.17,
        "brokerage_rt": 40,
        "net_loss": 105.08,
        "net_profit": 90.17,
        "eff_rr": 0.86,
        "sq_state": "RELEASED",
        "mom_val": -61.250939,
        "nearest_support": 1635.130005,
        "support_pct": -1.44,
        "nearest_resistance": 1701.579956,
        "resistance_pct": 2.57,
        "bb_upper": 1772.859713,
        "bb_mid": 1708.679004,
        "bb_lower": 1644.498295,
        "kc_upper": 1729.447857,
        "kc_lower": 1687.910151,
        "atr": 14.46325315,
        "swing_high": 1777.0,
        "swing_high_pct": 7.12,
        "swing_low": 1635.130005,
        "swing_low_pct": -1.44,
        "volume_ratio": 1.8,
        "volume_expanding": true,
        "volume_today": 301614080,
        "volume_avg": 167518208
      },
      "analysis": "ETH (CRYPTO) short scalp \u2014 squeeze released. momentum \u25bc -61.2509. Resistance $1701.5800. Stop $1680.6348 (1.3% risk), target $1615.5502 (2.0:1 R:R)."
    },
    {
      "symbol": "LINK",
      "name": "Chainlink",
      "sector": "Crypto",
      "asset_type": "crypto",
      "dir": "SHORT",
      "grade": "B",
      "score": 5,
      "score_max": 10,
      "chips": [
        "MOMENTUM ALIGNED",
        "RESISTANCE @ 7.7650",
        "VOLUME EXPANSION"
      ],
      "weekly": false,
      "low_rr": false,
      "rr_text": "2.0:1",
      "target_2r": false,
      "liquidity": "LIQUID",
      "price": 7.60900021,
      "y_close": 7.60900021,
      "open": 7.60900021,
      "open_pct": 0.0,
      "current_pct": 0.0,
      "day_pct": 0.0,
      "entry": 7.60900021,
      "stop": 7.71986562,
      "target": 7.38726939,
      "rr": 2.0,
      "atr": 0.07391027,
      "adx": 29.37,
      "market_regime": "trending",
      "trail": 7.71986562,
      "stop_pct": 1.5,
      "p2_pct": 2.9,
      "target_basis": "atr",
      "spark": [
        7.9000001,
        7.954,
        7.98000002,
        7.97399998,
        7.98699999,
        8.07600021,
        8.10400009,
        8.13700008,
        8.00800037,
        7.97300005,
        7.97599983,
        7.94700003,
        7.89499998,
        7.90899992,
        7.91200018,
        7.89099979,
        7.84700012,
        7.86499977,
        7.86199999,
        7.875,
        7.89599991,
        7.89300013,
        7.83099985,
        7.82299995,
        7.69199991,
        7.65100002,
        7.51900005,
        7.53499985,
        7.53999996,
        7.60900021
      ],
      "trend": "blue",
      "turnover": 0,
      "detail": {
        "setup_type": "scalp",
        "entry": 7.609,
        "stop": 7.719866,
        "target": 7.387269,
        "stop_pct": 1.46,
        "target_pct": 2.91,
        "notional": 5000,
        "units": 657,
        "risk_dollars": 72.84,
        "reward_dollars": 145.68,
        "brokerage_rt": 40,
        "net_loss": 112.84,
        "net_profit": 105.68,
        "eff_rr": 0.94,
        "sq_state": "RELEASED",
        "mom_val": -0.274302,
        "nearest_support": 7.484,
        "support_pct": -1.64,
        "nearest_resistance": 7.765,
        "resistance_pct": 2.05,
        "bb_upper": 8.087071,
        "bb_mid": 7.7984,
        "bb_lower": 7.509729,
        "kc_upper": 7.905136,
        "kc_lower": 7.691664,
        "atr": 0.07391027,
        "swing_high": 8.144,
        "swing_high_pct": 7.03,
        "swing_low": 7.484,
        "swing_low_pct": -1.64,
        "volume_ratio": 1.54,
        "volume_expanding": true,
        "volume_today": 4080944,
        "volume_avg": 2641519
      },
      "analysis": "LINK (CRYPTO) short scalp \u2014 squeeze released. momentum \u25bc -0.2743. Resistance $7.7650. Stop $7.7199 (1.5% risk), target $7.3873 (2.0:1 R:R)."
    },
    {
      "symbol": "LTC",
      "name": "Litecoin",
      "sector": "Crypto",
      "asset_type": "crypto",
      "dir": "SHORT",
      "grade": "B",
      "score": 5,
      "score_max": 10,
      "chips": [
        "MOMENTUM ALIGNED",
        "RESISTANCE @ 44.2600",
        "VOLUME EXPANSION"
      ],
      "weekly": false,
      "low_rr": false,
      "rr_text": "2.0:1",
      "target_2r": false,
      "liquidity": "LIQUID",
      "price": 43.5,
      "y_close": 43.5,
      "open": 43.5,
      "open_pct": 0.0,
      "current_pct": 0.0,
      "day_pct": 0.0,
      "entry": 43.5,
      "stop": 43.9847758,
      "target": 42.5304484,
      "rr": 2.0,
      "atr": 0.32318387,
      "adx": 30.68,
      "market_regime": "trending",
      "trail": 43.9847758,
      "stop_pct": 1.1,
      "p2_pct": 2.2,
      "target_basis": "atr",
      "spark": [
        44.79999924,
        44.95000076,
        44.81999969,
        44.81000137,
        44.74000168,
        45.20000076,
        45.5,
        45.65000153,
        45.15999985,
        45.09000015,
        45.04000092,
        44.88000107,
        44.68999863,
        44.59999847,
        44.52000046,
        44.63999939,
        44.49000168,
        44.52000046,
        44.52999878,
        44.52999878,
        44.54999924,
        44.54999924,
        44.36999893,
        44.31000137,
        43.90000153,
        43.75,
        43.27000046,
        43.31999969,
        43.33000183,
        43.5
      ],
      "trend": "blue",
      "turnover": 0,
      "detail": {
        "setup_type": "scalp",
        "entry": 43.5,
        "stop": 43.984776,
        "target": 42.530448,
        "stop_pct": 1.11,
        "target_pct": 2.23,
        "notional": 5000,
        "units": 114,
        "risk_dollars": 55.26,
        "reward_dollars": 110.53,
        "brokerage_rt": 40,
        "net_loss": 95.26,
        "net_profit": 70.53,
        "eff_rr": 0.74,
        "sq_state": "RELEASED",
        "mom_val": -1.061275,
        "nearest_support": 43.080002,
        "support_pct": -0.97,
        "nearest_resistance": 44.259998,
        "resistance_pct": 1.75,
        "bb_upper": 45.327504,
        "bb_mid": 44.2645,
        "bb_lower": 43.201496,
        "kc_upper": 44.746952,
        "kc_lower": 43.782048,
        "atr": 0.32318387,
        "swing_high": 46.009998,
        "swing_high_pct": 5.77,
        "swing_low": 43.080002,
        "swing_low_pct": -0.97,
        "volume_ratio": 2.5,
        "volume_expanding": true,
        "volume_today": 3326096,
        "volume_avg": 1330728
      },
      "analysis": "LTC (CRYPTO) short scalp \u2014 squeeze released. momentum \u25bc -1.0613. Resistance $44.2600. Stop $43.9848 (1.1% risk), target $42.5304 (2.0:1 R:R)."
    },
    {
      "symbol": "NAS100",
      "name": "Nasdaq 100",
      "sector": "Index",
      "asset_type": "index",
      "dir": "SHORT",
      "grade": "B",
      "score": 4,
      "score_max": 10,
      "chips": [
        "MOMENTUM ALIGNED",
        "RESISTANCE @ 30337.5000"
      ],
      "weekly": false,
      "low_rr": false,
      "rr_text": "2.0:1",
      "target_2r": false,
      "liquidity": "LIQUID",
      "price": 29833.5,
      "y_close": 29833.5,
      "open": 29833.5,
      "open_pct": 0.0,
      "current_pct": 0.0,
      "day_pct": 0.0,
      "entry": 29833.5,
      "stop": 30032.65049261,
      "target": 29435.19901479,
      "rr": 2.0,
      "atr": 132.76699507,
      "adx": 43.68,
      "market_regime": "trending",
      "trail": 30032.65049261,
      "stop_pct": 0.7,
      "p2_pct": 1.3,
      "target_basis": "atr",
      "spark": [
        30640.25,
        30736.75,
        30759.0,
        30731.25,
        30699.0,
        30720.0,
        30757.75,
        30800.5,
        30937.0,
        30639.0,
        30557.25,
        30589.0,
        30615.0,
        30558.5,
        30654.0,
        30662.5,
        30582.25,
        30575.0,
        30602.0,
        30459.75,
        30405.25,
        30383.0,
        30242.5,
        30108.5,
        29969.75,
        29909.0,
        29827.25,
        29886.25,
        29818.0,
        29833.5
      ],
      "trend": "blue",
      "turnover": 0,
      "detail": {
        "setup_type": "scalp",
        "entry": 29833.5,
        "stop": 30032.650493,
        "target": 29435.199015,
        "stop_pct": 0.67,
        "target_pct": 1.34,
        "notional": 5000,
        "units": 0,
        "risk_dollars": 0.0,
        "reward_dollars": 0.0,
        "brokerage_rt": 40,
        "net_loss": 40.0,
        "net_profit": -40.0,
        "eff_rr": -1.0,
        "sq_state": "RELEASED",
        "mom_val": -604.446955,
        "nearest_support": null,
        "support_pct": null,
        "nearest_resistance": 30337.5,
        "resistance_pct": 1.69,
        "bb_upper": 30945.341744,
        "bb_mid": 30311.9125,
        "bb_lower": 29678.483256,
        "kc_upper": 30507.468043,
        "kc_lower": 30116.356957,
        "atr": 132.76699507,
        "swing_high": 30968.0,
        "swing_high_pct": 3.8,
        "swing_low": 29752.0,
        "swing_low_pct": -0.27,
        "volume_ratio": 0.47,
        "volume_expanding": false,
        "volume_today": 11599,
        "volume_avg": 24523
      },
      "analysis": "NAS100 (INDEX) short scalp \u2014 squeeze released. momentum \u25bc -604.4470. Resistance $30337.5000. Stop $30032.6505 (0.7% risk), target $29435.1990 (2.0:1 R:R)."
    },
    {
      "symbol": "US30",
      "name": "Dow Jones 30",
      "sector": "Index",
      "asset_type": "index",
      "dir": "SHORT",
      "grade": "B",
      "score": 4,
      "score_max": 10,
      "chips": [
        "MOMENTUM ALIGNED",
        "RESISTANCE @ 51888.0000"
      ],
      "weekly": false,
      "low_rr": false,
      "rr_text": "2.0:1",
      "target_2r": false,
      "liquidity": "LIQUID",
      "price": 51866.0,
      "y_close": 51866.0,
      "open": 51866.0,
      "open_pct": 0.0,
      "current_pct": 0.0,
      "day_pct": 0.0,
      "entry": 51866.0,
      "stop": 52097.70882519,
      "target": 51402.58234962,
      "rr": 2.0,
      "atr": 154.47255013,
      "adx": 27.47,
      "market_regime": "trending",
      "trail": 52097.70882519,
      "stop_pct": 0.4,
      "p2_pct": 0.9,
      "target_basis": "atr",
      "spark": [
        51897.0,
        51976.0,
        51948.0,
        51966.0,
        51966.0,
        52001.0,
        52048.0,
        52043.0,
        52256.0,
        52136.0,
        52168.0,
        52167.0,
        52113.0,
        52026.0,
        52113.0,
        51888.0,
        52145.0,
        52152.0,
        52250.0,
        52172.0,
        52136.0,
        52090.0,
        51991.0,
        51943.0,
        51861.0,
        51730.0,
        51779.0,
        51869.0,
        51842.0,
        51866.0
      ],
      "trend": "blue",
      "turnover": 0,
      "detail": {
        "setup_type": "scalp",
        "entry": 51866.0,
        "stop": 52097.708825,
        "target": 51402.58235,
        "stop_pct": 0.45,
        "target_pct": 0.89,
        "notional": 5000,
        "units": 0,
        "risk_dollars": 0.0,
        "reward_dollars": 0.0,
        "brokerage_rt": 40,
        "net_loss": 40.0,
        "net_profit": -40.0,
        "eff_rr": -1.0,
        "sq_state": "RELEASED",
        "mom_val": -275.345192,
        "nearest_support": 51804.0,
        "support_pct": -0.12,
        "nearest_resistance": 51888.0,
        "resistance_pct": 0.04,
        "bb_upper": 52317.580313,
        "bb_mid": 52015.05,
        "bb_lower": 51712.519687,
        "kc_upper": 52248.6436,
        "kc_lower": 51781.4564,
        "atr": 154.47255013,
        "swing_high": 52378.0,
        "swing_high_pct": 0.99,
        "swing_low": 51691.0,
        "swing_low_pct": -0.34,
        "volume_ratio": 0.54,
        "volume_expanding": false,
        "volume_today": 1744,
        "volume_avg": 3240
      },
      "analysis": "US30 (INDEX) short scalp \u2014 squeeze released. momentum \u25bc -275.3452. Resistance $51888.0000. Stop $52097.7088 (0.4% risk), target $51402.5823 (2.0:1 R:R)."
    },
    {
      "symbol": "BTC",
      "name": "Bitcoin",
      "sector": "Crypto",
      "asset_type": "crypto",
      "dir": "SHORT",
      "grade": "B",
      "score": 4,
      "score_max": 10,
      "chips": [
        "MOMENTUM ALIGNED",
        "RESISTANCE @ 63208.3516"
      ],
      "weekly": false,
      "low_rr": false,
      "rr_text": "2.0:1",
      "target_2r": false,
      "liquidity": "LIQUID",
      "price": 62400.0,
      "y_close": 62400.0,
      "open": 62400.0,
      "open_pct": 0.0,
      "current_pct": 0.0,
      "day_pct": 0.0,
      "entry": 62400.0,
      "stop": 63001.38771832,
      "target": 61197.22456336,
      "rr": 2.0,
      "atr": 400.92514555,
      "adx": 29.55,
      "market_regime": "trending",
      "trail": 63001.38771832,
      "stop_pct": 1.0,
      "p2_pct": 1.9,
      "target_basis": "atr",
      "spark": [
        63910.01171875,
        64131.3984375,
        64089.58984375,
        64074.578125,
        64066.37109375,
        64582.23828125,
        65077.578125,
        65502.76953125,
        64896.1015625,
        64765.421875,
        64641.08984375,
        64529.19921875,
        64264.73828125,
        64431.01953125,
        64359.171875,
        64246.41015625,
        63889.98828125,
        63950.609375,
        64069.328125,
        64078.71875,
        64122.71875,
        63987.8203125,
        63538.0,
        63321.01171875,
        62861.8984375,
        62805.5,
        62308.1484375,
        62307.1015625,
        62237.25,
        62400.0
      ],
      "trend": "blue",
      "turnover": 0,
      "detail": {
        "setup_type": "scalp",
        "entry": 62400.0,
        "stop": 63001.387718,
        "target": 61197.224563,
        "stop_pct": 0.96,
        "target_pct": 1.93,
        "notional": 5000,
        "units": 0,
        "risk_dollars": 0.0,
        "reward_dollars": 0.0,
        "brokerage_rt": 40,
        "net_loss": 40.0,
        "net_profit": -40.0,
        "eff_rr": -1.0,
        "sq_state": "RELEASED",
        "mom_val": -1554.906409,
        "nearest_support": 61887.738281,
        "support_pct": -0.82,
        "nearest_resistance": 63208.351562,
        "resistance_pct": 1.3,
        "bb_upper": 65232.613347,
        "bb_mid": 63617.486133,
        "bb_lower": 62002.358918,
        "kc_upper": 64204.787471,
        "kc_lower": 63030.184794,
        "atr": 400.92514555,
        "swing_high": 65550.0,
        "swing_high_pct": 5.05,
        "swing_low": 61887.738281,
        "swing_low_pct": -0.82,
        "volume_ratio": 1.03,
        "volume_expanding": false,
        "volume_today": 650364928,
        "volume_avg": 630061056
      },
      "analysis": "BTC (CRYPTO) short scalp \u2014 squeeze released. momentum \u25bc -1554.9064. Resistance $63208.3516. Stop $63001.3877 (1.0% risk), target $61197.2246 (2.0:1 R:R)."
    },
    {
      "symbol": "SOL",
      "name": "Solana",
      "sector": "Crypto",
      "asset_type": "crypto",
      "dir": "SHORT",
      "grade": "B",
      "score": 4,
      "score_max": 10,
      "chips": [
        "MOMENTUM ALIGNED",
        "RESISTANCE @ 71.2600"
      ],
      "weekly": false,
      "low_rr": false,
      "rr_text": "2.0:1",
      "target_2r": false,
      "liquidity": "LIQUID",
      "price": 69.13999939,
      "y_close": 69.13999939,
      "open": 69.13999939,
      "open_pct": 0.0,
      "current_pct": 0.0,
      "day_pct": 0.0,
      "entry": 69.13999939,
      "stop": 70.22615366,
      "target": 66.96769084,
      "rr": 2.0,
      "atr": 0.72410285,
      "adx": 37.63,
      "market_regime": "trending",
      "trail": 70.22615366,
      "stop_pct": 1.6,
      "p2_pct": 3.1,
      "target_basis": "atr",
      "spark": [
        73.61000061,
        74.01999664,
        73.81999969,
        73.72000122,
        73.69999695,
        74.09999847,
        74.33000183,
        74.88999939,
        73.37000275,
        73.05999756,
        72.87000275,
        73.19999695,
        72.54000092,
        72.68000031,
        72.73999786,
        72.63999939,
        72.02999878,
        71.87999725,
        71.80000305,
        71.65000153,
        71.91999817,
        71.91000366,
        71.36000061,
        70.94000244,
        70.23999786,
        69.90000153,
        68.62000275,
        68.83000183,
        68.73000336,
        69.13999939
      ],
      "trend": "blue",
      "turnover": 0,
      "detail": {
        "setup_type": "scalp",
        "entry": 69.139999,
        "stop": 70.226154,
        "target": 66.967691,
        "stop_pct": 1.57,
        "target_pct": 3.14,
        "notional": 5000,
        "units": 72,
        "risk_dollars": 78.2,
        "reward_dollars": 156.41,
        "brokerage_rt": 40,
        "net_loss": 118.2,
        "net_profit": 116.41,
        "eff_rr": 0.98,
        "sq_state": "RELEASED",
        "mom_val": -2.692442,
        "nearest_support": 68.110001,
        "support_pct": -1.49,
        "nearest_resistance": 71.260002,
        "resistance_pct": 3.07,
        "bb_upper": 74.21861,
        "bb_mid": 71.281001,
        "bb_lower": 68.343391,
        "kc_upper": 72.354658,
        "kc_lower": 70.207343,
        "atr": 0.72410285,
        "swing_high": 74.910004,
        "swing_high_pct": 8.35,
        "swing_low": 68.110001,
        "swing_low_pct": -1.49,
        "volume_ratio": 0.38,
        "volume_expanding": false,
        "volume_today": 11790080,
        "volume_avg": 30829273
      },
      "analysis": "SOL (CRYPTO) short scalp \u2014 squeeze released. momentum \u25bc -2.6924. Resistance $71.2600. Stop $70.2262 (1.6% risk), target $66.9677 (2.0:1 R:R)."
    },
    {
      "symbol": "XRP",
      "name": "XRP",
      "sector": "Crypto",
      "asset_type": "crypto",
      "dir": "SHORT",
      "grade": "B",
      "score": 4,
      "score_max": 10,
      "chips": [
        "MOMENTUM ALIGNED",
        "RESISTANCE @ 1.1206"
      ],
      "weekly": false,
      "low_rr": false,
      "rr_text": "2.0:1",
      "target_2r": false,
      "liquidity": "LIQUID",
      "price": 1.10739994,
      "y_close": 1.10739994,
      "open": 1.10739994,
      "open_pct": 0.0,
      "current_pct": 0.0,
      "day_pct": 0.0,
      "entry": 1.10739994,
      "stop": 1.11977301,
      "target": 1.0826538,
      "rr": 2.0,
      "atr": 0.00824871,
      "adx": 26.76,
      "market_regime": "trending",
      "trail": 1.11977301,
      "stop_pct": 1.1,
      "p2_pct": 2.2,
      "target_basis": "atr",
      "spark": [
        1.12950003,
        1.13600004,
        1.13390005,
        1.13390005,
        1.13639998,
        1.14690006,
        1.15670002,
        1.16240001,
        1.14180005,
        1.13870001,
        1.13740003,
        1.13839996,
        1.13170004,
        1.13329995,
        1.13059998,
        1.13030005,
        1.12629998,
        1.12839997,
        1.13020003,
        1.12769997,
        1.12849998,
        1.12609994,
        1.1164,
        1.11479998,
        1.11199999,
        1.11160004,
        1.09909999,
        1.10259998,
        1.10290003,
        1.10739994
      ],
      "trend": "blue",
      "turnover": 0,
      "detail": {
        "setup_type": "scalp",
        "entry": 1.1074,
        "stop": 1.119773,
        "target": 1.082654,
        "stop_pct": 1.12,
        "target_pct": 2.23,
        "notional": 5000,
        "units": 4515,
        "risk_dollars": 55.86,
        "reward_dollars": 111.73,
        "brokerage_rt": 40,
        "net_loss": 95.86,
        "net_profit": 71.73,
        "eff_rr": 0.75,
        "sq_state": "RELEASED",
        "mom_val": -0.023289,
        "nearest_support": 1.0935,
        "support_pct": -1.26,
        "nearest_resistance": 1.1206,
        "resistance_pct": 1.19,
        "bb_upper": 1.145694,
        "bb_mid": 1.121785,
        "bb_lower": 1.097876,
        "kc_upper": 1.134168,
        "kc_lower": 1.109402,
        "atr": 0.00824871,
        "swing_high": 1.1626,
        "swing_high_pct": 4.98,
        "swing_low": 1.0935,
        "swing_low_pct": -1.26,
        "volume_ratio": 0.61,
        "volume_expanding": false,
        "volume_today": 11705600,
        "volume_avg": 19286912
      },
      "analysis": "XRP (CRYPTO) short scalp \u2014 squeeze released. momentum \u25bc -0.0233. Resistance $1.1206. Stop $1.1198 (1.1% risk), target $1.0827 (2.0:1 R:R)."
    },
    {
      "symbol": "ADA",
      "name": "Cardano",
      "sector": "Crypto",
      "asset_type": "crypto",
      "dir": "SHORT",
      "grade": "B",
      "score": 4,
      "score_max": 10,
      "chips": [
        "MOMENTUM ALIGNED",
        "RESISTANCE @ 0.1564"
      ],
      "weekly": false,
      "low_rr": false,
      "rr_text": "2.0:1",
      "target_2r": false,
      "liquidity": "LIQUID",
      "price": 0.1534,
      "y_close": 0.1534,
      "open": 0.1534,
      "open_pct": 0.0,
      "current_pct": 0.0,
      "day_pct": 0.0,
      "entry": 0.1534,
      "stop": 0.15598463,
      "target": 0.14823073,
      "rr": 2.0,
      "atr": 0.00172309,
      "adx": 29.26,
      "market_regime": "trending",
      "trail": 0.15598463,
      "stop_pct": 1.7,
      "p2_pct": 3.4,
      "target_basis": "atr",
      "spark": [
        0.1602,
        0.16150001,
        0.161,
        0.1602,
        0.16,
        0.16159999,
        0.1617,
        0.1629,
        0.16,
        0.1593,
        0.1593,
        0.1594,
        0.1584,
        0.15880001,
        0.15889999,
        0.1591,
        0.15800001,
        0.1584,
        0.15899999,
        0.15880001,
        0.1591,
        0.15970001,
        0.1582,
        0.1574,
        0.15449999,
        0.15440001,
        0.1524,
        0.1524,
        0.15260001,
        0.1534
      ],
      "trend": "blue",
      "turnover": 0,
      "detail": {
        "setup_type": "scalp",
        "entry": 0.1534,
        "stop": 0.155985,
        "target": 0.148231,
        "stop_pct": 1.68,
        "target_pct": 3.37,
        "notional": 5000,
        "units": 32594,
        "risk_dollars": 84.24,
        "reward_dollars": 168.49,
        "brokerage_rt": 40,
        "net_loss": 124.24,
        "net_profit": 128.49,
        "eff_rr": 1.03,
        "sq_state": "RELEASED",
        "mom_val": -0.004797,
        "nearest_support": 0.1509,
        "support_pct": -1.63,
        "nearest_resistance": 0.1564,
        "resistance_pct": 1.96,
        "bb_upper": 0.16231,
        "bb_mid": 0.15711,
        "bb_lower": 0.15191,
        "kc_upper": 0.15962,
        "kc_lower": 0.1546,
        "atr": 0.00172309,
        "swing_high": 0.1634,
        "swing_high_pct": 6.52,
        "swing_low": 0.1509,
        "swing_low_pct": -1.63,
        "volume_ratio": 0.55,
        "volume_expanding": false,
        "volume_today": 2564992,
        "volume_avg": 4696900
      },
      "analysis": "ADA (CRYPTO) short scalp \u2014 squeeze released. momentum \u25bc -0.0048. Resistance $0.1564. Stop $0.1560 (1.7% risk), target $0.1482 (2.0:1 R:R)."
    },
    {
      "symbol": "DOGE",
      "name": "Dogecoin",
      "sector": "Crypto",
      "asset_type": "crypto",
      "dir": "SHORT",
      "grade": "B",
      "score": 4,
      "score_max": 10,
      "chips": [
        "MOMENTUM ALIGNED",
        "RESISTANCE @ 0.0813"
      ],
      "weekly": false,
      "low_rr": false,
      "rr_text": "2.0:1",
      "target_2r": false,
      "liquidity": "LIQUID",
      "price": 0.07945,
      "y_close": 0.07945,
      "open": 0.07945,
      "open_pct": 0.0,
      "current_pct": 0.0,
      "day_pct": 0.0,
      "entry": 0.07945,
      "stop": 0.08044995,
      "target": 0.07745011,
      "rr": 2.0,
      "atr": 0.00066663,
      "adx": 44.81,
      "market_regime": "trending",
      "trail": 0.08044995,
      "stop_pct": 1.3,
      "p2_pct": 2.5,
      "target_basis": "atr",
      "spark": [
        0.08311,
        0.0834,
        0.0835,
        0.08362,
        0.08357,
        0.08416,
        0.0845,
        0.08492,
        0.08386,
        0.08354,
        0.08329,
        0.08321,
        0.08278,
        0.08273,
        0.08276,
        0.0826,
        0.08214,
        0.08238,
        0.0825,
        0.08181,
        0.08219,
        0.08212,
        0.08159,
        0.0816,
        0.08017,
        0.07988,
        0.07905,
        0.0789,
        0.07901,
        0.07945
      ],
      "trend": "blue",
      "turnover": 0,
      "detail": {
        "setup_type": "scalp",
        "entry": 0.07945,
        "stop": 0.08045,
        "target": 0.07745,
        "stop_pct": 1.26,
        "target_pct": 2.52,
        "notional": 5000,
        "units": 62932,
        "risk_dollars": 62.93,
        "reward_dollars": 125.86,
        "brokerage_rt": 40,
        "net_loss": 102.93,
        "net_profit": 85.86,
        "eff_rr": 0.83,
        "sq_state": "RELEASED",
        "mom_val": -0.002754,
        "nearest_support": 0.0784,
        "support_pct": -1.32,
        "nearest_resistance": 0.08133,
        "resistance_pct": 2.37,
        "bb_upper": 0.084434,
        "bb_mid": 0.081508,
        "bb_lower": 0.078582,
        "kc_upper": 0.082464,
        "kc_lower": 0.080552,
        "atr": 0.00066663,
        "swing_high": 0.08496,
        "swing_high_pct": 6.94,
        "swing_low": 0.0784,
        "swing_low_pct": -1.32,
        "volume_ratio": 0.44,
        "volume_expanding": false,
        "volume_today": 5768128,
        "volume_avg": 13171676
      },
      "analysis": "DOGE (CRYPTO) short scalp \u2014 squeeze released. momentum \u25bc -0.0028. Resistance $0.0813. Stop $0.0804 (1.3% risk), target $0.0775 (2.0:1 R:R)."
    },
    {
      "symbol": "DOT",
      "name": "Polkadot",
      "sector": "Crypto",
      "asset_type": "crypto",
      "dir": "SHORT",
      "grade": "B",
      "score": 4,
      "score_max": 10,
      "chips": [
        "MOMENTUM ALIGNED",
        "RESISTANCE @ 0.9270"
      ],
      "weekly": false,
      "low_rr": false,
      "rr_text": "2.0:1",
      "target_2r": false,
      "liquidity": "LIQUID",
      "price": 0.903,
      "y_close": 0.903,
      "open": 0.903,
      "open_pct": 0.0,
      "current_pct": 0.0,
      "day_pct": 0.0,
      "entry": 0.903,
      "stop": 0.91729244,
      "target": 0.87441513,
      "rr": 2.0,
      "atr": 0.00952829,
      "adx": 38.55,
      "market_regime": "trending",
      "trail": 0.91729244,
      "stop_pct": 1.6,
      "p2_pct": 3.2,
      "target_basis": "atr",
      "spark": [
        0.958,
        0.96200001,
        0.96200001,
        0.95899999,
        0.958,
        0.97000003,
        0.972,
        0.977,
        0.96600002,
        0.95599997,
        0.96100003,
        0.95499998,
        0.94599998,
        0.94400001,
        0.94599998,
        0.94300002,
        0.93300003,
        0.935,
        0.93199998,
        0.93300003,
        0.93599999,
        0.93699998,
        0.92900002,
        0.93000001,
        0.91100001,
        0.90499997,
        0.88999999,
        0.89499998,
        0.89499998,
        0.903
      ],
      "trend": "blue",
      "turnover": 0,
      "detail": {
        "setup_type": "scalp",
        "entry": 0.903,
        "stop": 0.917292,
        "target": 0.874415,
        "stop_pct": 1.58,
        "target_pct": 3.17,
        "notional": 5000,
        "units": 5537,
        "risk_dollars": 79.14,
        "reward_dollars": 158.27,
        "brokerage_rt": 40,
        "net_loss": 119.14,
        "net_profit": 118.27,
        "eff_rr": 0.99,
        "sq_state": "RELEASED",
        "mom_val": -0.036129,
        "nearest_support": 0.884,
        "support_pct": -2.1,
        "nearest_resistance": 0.927,
        "resistance_pct": 2.66,
        "bb_upper": 0.968636,
        "bb_mid": 0.92795,
        "bb_lower": 0.887264,
        "kc_upper": 0.941668,
        "kc_lower": 0.914232,
        "atr": 0.00952829,
        "swing_high": 0.978,
        "swing_high_pct": 8.31,
        "swing_low": 0.884,
        "swing_low_pct": -2.1,
        "volume_ratio": 1.0,
        "volume_expanding": false,
        "volume_today": 1125296,
        "volume_avg": 1130353
      },
      "analysis": "DOT (CRYPTO) short scalp \u2014 squeeze released. momentum \u25bc -0.0361. Resistance $0.9270. Stop $0.9173 (1.6% risk), target $0.8744 (2.0:1 R:R)."
    },
    {
      "symbol": "BCH",
      "name": "Bitcoin Cash",
      "sector": "Crypto",
      "asset_type": "crypto",
      "dir": "SHORT",
      "grade": "B",
      "score": 4,
      "score_max": 10,
      "chips": [
        "MOMENTUM ALIGNED",
        "RESISTANCE @ 193.4400"
      ],
      "weekly": false,
      "low_rr": false,
      "rr_text": "2.0:1",
      "target_2r": false,
      "liquidity": "LIQUID",
      "price": 191.07000732,
      "y_close": 191.07000732,
      "open": 191.07000732,
      "open_pct": 0.0,
      "current_pct": 0.0,
      "day_pct": 0.0,
      "entry": 191.07000732,
      "stop": 194.27322392,
      "target": 184.66357412,
      "rr": 2.0,
      "atr": 2.13547773,
      "adx": 34.74,
      "market_regime": "trending",
      "trail": 194.27322392,
      "stop_pct": 1.7,
      "p2_pct": 3.4,
      "target_basis": "atr",
      "spark": [
        199.05000305,
        199.03999329,
        199.55999756,
        199.1499939,
        198.99000549,
        200.99000549,
        202.17999268,
        204.38999939,
        201.00999451,
        201.11000061,
        198.94000244,
        198.80000305,
        197.57000732,
        198.53999329,
        198.52000427,
        198.55000305,
        196.71000671,
        197.47000122,
        195.6000061,
        196.1000061,
        195.61000061,
        195.72999573,
        194.88000488,
        194.52000427,
        190.80999756,
        190.83000183,
        188.55999756,
        189.69999695,
        190.19999695,
        191.07000732
      ],
      "trend": "blue",
      "turnover": 0,
      "detail": {
        "setup_type": "scalp",
        "entry": 191.070007,
        "stop": 194.273224,
        "target": 184.663574,
        "stop_pct": 1.68,
        "target_pct": 3.35,
        "notional": 5000,
        "units": 26,
        "risk_dollars": 83.28,
        "reward_dollars": 166.57,
        "brokerage_rt": 40,
        "net_loss": 123.28,
        "net_profit": 126.57,
        "eff_rr": 1.03,
        "sq_state": "RELEASED",
        "mom_val": -5.896431,
        "nearest_support": 186.589996,
        "support_pct": -2.34,
        "nearest_resistance": 193.440002,
        "resistance_pct": 1.24,
        "bb_upper": 201.699351,
        "bb_mid": 194.935502,
        "bb_lower": 188.171653,
        "kc_upper": 198.035411,
        "kc_lower": 191.835593,
        "atr": 2.13547773,
        "swing_high": 205.080002,
        "swing_high_pct": 7.33,
        "swing_low": 186.589996,
        "swing_low_pct": -2.34,
        "volume_ratio": 0.22,
        "volume_expanding": false,
        "volume_today": 1327840,
        "volume_avg": 6134190
      },
      "analysis": "BCH (CRYPTO) short scalp \u2014 squeeze released. momentum \u25bc -5.8964. Resistance $193.4400. Stop $194.2732 (1.7% risk), target $184.6636 (2.0:1 R:R)."
    }
  ]
}